{"nm":"passive_lvl_2","ddd":0,"h":1252,"w":1112,"meta":{"g":"LottieFiles Figma v42"},"layers":[{"ty":4,"nm":"2 / Group / Vector","sr":1,"st":0,"op":31,"ip":0,"hd":false,"ddd":0,"bm":0,"hasMask":false,"ao":0,"ks":{"a":{"a":1,"k":[{"o":{"x":0,"y":0},"i":{"x":0.58,"y":1},"s":[55.6,21.26],"t":0},{"o":{"x":0.65,"y":0},"i":{"x":0.35,"y":0},"s":[59.74,19.96],"t":18},{"o":{"x":0,"y":0},"i":{"x":0.58,"y":1},"s":[51.64,23.57],"t":24},{"s":[55.6,21.26],"t":30}]},"s":{"a":1,"k":[{"o":{"x":0,"y":0},"i":{"x":0.58,"y":1},"s":[100,100],"t":0},{"o":{"x":0.65,"y":0},"i":{"x":0.35,"y":0},"s":[100,100],"t":18},{"o":{"x":0,"y":0},"i":{"x":0.58,"y":1},"s":[100,100],"t":24},{"s":[100,100],"t":30}]},"sk":{"a":0,"k":0},"p":{"a":1,"k":[{"o":{"x":0,"y":0},"i":{"x":0.58,"y":1},"s":[254.67,1147.71],"t":0},{"o":{"x":0.65,"y":0},"i":{"x":0.35,"y":0},"s":[232.28,1154.11],"t":18},{"o":{"x":0,"y":0},"i":{"x":0.58,"y":1},"s":[276.18,1136.3],"t":24},{"s":[254.67,1147.71],"t":30}]},"r":{"a":1,"k":[{"o":{"x":0,"y":0},"i":{"x":0.58,"y":1},"s":[0],"t":0},{"o":{"x":0.65,"y":0},"i":{"x":0.35,"y":0},"s":[0],"t":18},{"o":{"x":0,"y":0},"i":{"x":0.58,"y":1},"s":[0],"t":24},{"s":[0],"t":30}]},"sa":{"a":0,"k":0},"o":{"a":1,"k":[{"o":{"x":0,"y":0},"i":{"x":0.58,"y":1},"s":[100],"t":0},{"o":{"x":0.65,"y":0},"i":{"x":0.35,"y":0},"s":[100],"t":18},{"o":{"x":0,"y":0},"i":{"x":0.58,"y":1},"s":[100],"t":24},{"s":[100],"t":30}]}},"shapes":[{"ty":"sh","bm":0,"hd":false,"nm":"","d":1,"ks":{"a":1,"k":[{"o":{"x":0,"y":0},"i":{"x":0.58,"y":1},"s":[{"c":true,"i":[[0,0],[-0.53,-2.15],[-12,48.03],[-0.47,2.18],[31.38,21.26]],"o":[[0.47,2.18],[11.99,48.03],[0.54,-2.15],[-31.39,21.26],[0,0]],"v":[[0,0],[1.51,6.49],[109.7,6.49],[111.21,0],[0,0]]}],"t":0},{"o":{"x":0.65,"y":0},"i":{"x":0.35,"y":0},"s":[{"c":true,"i":[[0,0],[-0.57,-2.02],[-12.89,45.1],[-0.5,2.05],[33.71,19.96]],"o":[[0.5,2.05],[12.88,45.1],[0.58,-2.02],[-33.72,19.96],[0,0]],"v":[[0,0],[1.62,6.09],[117.86,6.09],[119.48,0],[0,0]]}],"t":18},{"o":{"x":0,"y":0},"i":{"x":0.58,"y":1},"s":[{"c":true,"i":[[0,0],[-0.49,-2.38],[-11.14,53.26],[-0.44,2.42],[29.14,23.58]],"o":[[0.44,2.42],[11.13,53.26],[0.5,-2.38],[-29.15,23.58],[0,0]],"v":[[0,0],[1.4,7.2],[101.87,7.2],[103.27,0],[0,0]]}],"t":24},{"s":[{"c":true,"i":[[0,0],[-0.53,-2.15],[-12,48.03],[-0.47,2.18],[31.38,21.26]],"o":[[0.47,2.18],[11.99,48.03],[0.54,-2.15],[-31.39,21.26],[0,0]],"v":[[0,0],[1.51,6.49],[109.7,6.49],[111.21,0],[0,0]]}],"t":30}]}},{"ty":"fl","bm":0,"hd":false,"nm":"","c":{"a":1,"k":[{"o":{"x":0,"y":0},"i":{"x":0.58,"y":1},"s":[0.0236,0.4785,0.3804],"t":0},{"o":{"x":0.65,"y":0},"i":{"x":0.35,"y":0},"s":[0.0236,0.4785,0.3804],"t":18},{"o":{"x":0,"y":0},"i":{"x":0.58,"y":1},"s":[0.0236,0.4785,0.3804],"t":24},{"s":[0.0236,0.4785,0.3804],"t":30}]},"r":1,"o":{"a":1,"k":[{"o":{"x":0,"y":0},"i":{"x":0.58,"y":1},"s":[100],"t":0},{"o":{"x":0.65,"y":0},"i":{"x":0.35,"y":0},"s":[100],"t":18},{"o":{"x":0,"y":0},"i":{"x":0.58,"y":1},"s":[100],"t":24},{"s":[100],"t":30}]}}],"ind":1},{"ty":4,"nm":"2 / Group / Vector","sr":1,"st":0,"op":31,"ip":0,"hd":false,"ddd":0,"bm":0,"hasMask":false,"ao":0,"ks":{"a":{"a":1,"k":[{"o":{"x":0,"y":0},"i":{"x":0.58,"y":1},"s":[60.78,121.18],"t":0},{"o":{"x":0.65,"y":0},"i":{"x":0.35,"y":0},"s":[65.3,113.78],"t":18},{"o":{"x":0,"y":0},"i":{"x":0.58,"y":1},"s":[56.45,134.38],"t":24},{"s":[60.78,121.18],"t":30}]},"s":{"a":1,"k":[{"o":{"x":0,"y":0},"i":{"x":0.58,"y":1},"s":[100,100],"t":0},{"o":{"x":0.65,"y":0},"i":{"x":0.35,"y":0},"s":[100,100],"t":18},{"o":{"x":0,"y":0},"i":{"x":0.58,"y":1},"s":[100,100],"t":24},{"s":[100,100],"t":30}]},"sk":{"a":0,"k":0},"p":{"a":1,"k":[{"o":{"x":0,"y":0},"i":{"x":0.58,"y":1},"s":[254.68,1047.77],"t":0},{"o":{"x":0.65,"y":0},"i":{"x":0.35,"y":0},"s":[232.29,1060.28],"t":18},{"o":{"x":0,"y":0},"i":{"x":0.58,"y":1},"s":[276.19,1025.48],"t":24},{"s":[254.68,1047.77],"t":30}]},"r":{"a":1,"k":[{"o":{"x":0,"y":0},"i":{"x":0.58,"y":1},"s":[0],"t":0},{"o":{"x":0.65,"y":0},"i":{"x":0.35,"y":0},"s":[0],"t":18},{"o":{"x":0,"y":0},"i":{"x":0.58,"y":1},"s":[0],"t":24},{"s":[0],"t":30}]},"sa":{"a":0,"k":0},"o":{"a":1,"k":[{"o":{"x":0,"y":0},"i":{"x":0.58,"y":1},"s":[100],"t":0},{"o":{"x":0.65,"y":0},"i":{"x":0.35,"y":0},"s":[100],"t":18},{"o":{"x":0,"y":0},"i":{"x":0.58,"y":1},"s":[100],"t":24},{"s":[100],"t":30}]}},"shapes":[{"ty":"sh","bm":0,"hd":false,"nm":"","d":1,"ks":{"a":1,"k":[{"o":{"x":0,"y":0},"i":{"x":0.58,"y":1},"s":[{"c":true,"i":[[0,0],[-4.36,-17.44],[-12,48.03],[0,19.03],[37.21,36.75],[0,-60.52],[0,0]],"o":[[0,19.03],[11.99,48.03],[4.35,-17.44],[0,-60.51],[-37.21,36.74],[0,0],[0,0]],"v":[[0,151.46],[6.69,206.34],[114.88,206.34],[121.57,151.46],[60.79,0],[0.01,151.46],[0,151.46]]}],"t":0},{"o":{"x":0.65,"y":0},"i":{"x":0.35,"y":0},"s":[{"c":true,"i":[[0,0],[-4.68,-16.37],[-12.89,45.1],[0,17.87],[39.98,34.5],[0,-56.82],[0,0]],"o":[[0,17.87],[12.88,45.1],[4.67,-16.37],[0,-56.81],[-39.98,34.5],[0,0],[0,0]],"v":[[0,142.21],[7.19,193.73],[123.42,193.73],[130.61,142.21],[65.31,0],[0.01,142.21],[0,142.21]]}],"t":18},{"o":{"x":0,"y":0},"i":{"x":0.58,"y":1},"s":[{"c":true,"i":[[0,0],[-4.05,-19.34],[-11.14,53.26],[0,21.1],[34.55,40.75],[0,-67.11],[0,0]],"o":[[0,21.1],[11.13,53.26],[4.04,-19.34],[0,-67.1],[-34.55,40.74],[0,0],[0,0]],"v":[[0,167.95],[6.21,228.81],[106.68,228.81],[112.89,167.95],[56.45,0],[0.01,167.95],[0,167.95]]}],"t":24},{"s":[{"c":true,"i":[[0,0],[-4.36,-17.44],[-12,48.03],[0,19.03],[37.21,36.75],[0,-60.52],[0,0]],"o":[[0,19.03],[11.99,48.03],[4.35,-17.44],[0,-60.51],[-37.21,36.74],[0,0],[0,0]],"v":[[0,151.46],[6.69,206.34],[114.88,206.34],[121.57,151.46],[60.79,0],[0.01,151.46],[0,151.46]]}],"t":30}]}},{"ty":"fl","bm":0,"hd":false,"nm":"","c":{"a":1,"k":[{"o":{"x":0,"y":0},"i":{"x":0.58,"y":1},"s":[0.0353,0.553,0.451],"t":0},{"o":{"x":0.65,"y":0},"i":{"x":0.35,"y":0},"s":[0.0353,0.553,0.451],"t":18},{"o":{"x":0,"y":0},"i":{"x":0.58,"y":1},"s":[0.0353,0.553,0.451],"t":24},{"s":[0.0353,0.553,0.451],"t":30}]},"r":1,"o":{"a":1,"k":[{"o":{"x":0,"y":0},"i":{"x":0.58,"y":1},"s":[100],"t":0},{"o":{"x":0.65,"y":0},"i":{"x":0.35,"y":0},"s":[100],"t":18},{"o":{"x":0,"y":0},"i":{"x":0.58,"y":1},"s":[100],"t":24},{"s":[100],"t":30}]}}],"ind":2},{"ty":4,"nm":"2 / Group / Vector","sr":1,"st":0,"op":31,"ip":0,"hd":false,"ddd":0,"bm":0,"hasMask":false,"ao":0,"ks":{"a":{"a":1,"k":[{"o":{"x":0,"y":0},"i":{"x":0.58,"y":1},"s":[61.09,20.52],"t":0},{"o":{"x":0.65,"y":0},"i":{"x":0.35,"y":0},"s":[65.63,19.27],"t":18},{"o":{"x":0,"y":0},"i":{"x":0.58,"y":1},"s":[56.73,22.76],"t":24},{"s":[61.09,20.52],"t":30}]},"s":{"a":1,"k":[{"o":{"x":0,"y":0},"i":{"x":0.58,"y":1},"s":[100,100],"t":0},{"o":{"x":0.65,"y":0},"i":{"x":0.35,"y":0},"s":[100,100],"t":18},{"o":{"x":0,"y":0},"i":{"x":0.58,"y":1},"s":[100,100],"t":24},{"s":[100,100],"t":30}]},"sk":{"a":0,"k":0},"p":{"a":1,"k":[{"o":{"x":0,"y":0},"i":{"x":0.58,"y":1},"s":[254.67,1206.29],"t":0},{"o":{"x":0.65,"y":0},"i":{"x":0.35,"y":0},"s":[232.28,1209.11],"t":18},{"o":{"x":0,"y":0},"i":{"x":0.58,"y":1},"s":[276.17,1201.27],"t":24},{"s":[254.67,1206.29],"t":30}]},"r":{"a":1,"k":[{"o":{"x":0,"y":0},"i":{"x":0.58,"y":1},"s":[0],"t":0},{"o":{"x":0.65,"y":0},"i":{"x":0.35,"y":0},"s":[0],"t":18},{"o":{"x":0,"y":0},"i":{"x":0.58,"y":1},"s":[0],"t":24},{"s":[0],"t":30}]},"sa":{"a":0,"k":0},"o":{"a":1,"k":[{"o":{"x":0,"y":0},"i":{"x":0.58,"y":1},"s":[100],"t":0},{"o":{"x":0.65,"y":0},"i":{"x":0.35,"y":0},"s":[100],"t":18},{"o":{"x":0,"y":0},"i":{"x":0.58,"y":1},"s":[100],"t":24},{"s":[100],"t":30}]}},"shapes":[{"ty":"sh","bm":0,"hd":false,"nm":"","d":1,"ks":{"a":1,"k":[{"o":{"x":0,"y":0},"i":{"x":0.58,"y":1},"s":[{"c":true,"i":[[0,0],[0,0],[0,0],[0,0],[0,0]],"o":[[0,0],[0,0],[0,0],[0,0],[0,0]],"v":[[0,0],[122.18,0],[122.18,41.05],[0,41.05],[0,0]]}],"t":0},{"o":{"x":0.65,"y":0},"i":{"x":0.35,"y":0},"s":[{"c":true,"i":[[0,0],[0,0],[0,0],[0,0],[0,0]],"o":[[0,0],[0,0],[0,0],[0,0],[0,0]],"v":[[0,0],[131.26,0],[131.26,38.54],[0,38.54],[0,0]]}],"t":18},{"o":{"x":0,"y":0},"i":{"x":0.58,"y":1},"s":[{"c":true,"i":[[0,0],[0,0],[0,0],[0,0],[0,0]],"o":[[0,0],[0,0],[0,0],[0,0],[0,0]],"v":[[0,0],[113.46,0],[113.46,45.52],[0,45.52],[0,0]]}],"t":24},{"s":[{"c":true,"i":[[0,0],[0,0],[0,0],[0,0],[0,0]],"o":[[0,0],[0,0],[0,0],[0,0],[0,0]],"v":[[0,0],[122.18,0],[122.18,41.05],[0,41.05],[0,0]]}],"t":30}]}},{"ty":"fl","bm":0,"hd":false,"nm":"","c":{"a":1,"k":[{"o":{"x":0,"y":0},"i":{"x":0.58,"y":1},"s":[0.7804,0.7804,0.851],"t":0},{"o":{"x":0.65,"y":0},"i":{"x":0.35,"y":0},"s":[0.7804,0.7804,0.851],"t":18},{"o":{"x":0,"y":0},"i":{"x":0.58,"y":1},"s":[0.7804,0.7804,0.851],"t":24},{"s":[0.7804,0.7804,0.851],"t":30}]},"r":1,"o":{"a":1,"k":[{"o":{"x":0,"y":0},"i":{"x":0.58,"y":1},"s":[100],"t":0},{"o":{"x":0.65,"y":0},"i":{"x":0.35,"y":0},"s":[100],"t":18},{"o":{"x":0,"y":0},"i":{"x":0.58,"y":1},"s":[100],"t":24},{"s":[100],"t":30}]}}],"ind":3},{"ty":4,"nm":"2 / Group / Vector","sr":1,"st":0,"op":31,"ip":0,"hd":false,"ddd":0,"bm":0,"hasMask":false,"ao":0,"ks":{"a":{"a":1,"k":[{"o":{"x":0,"y":0},"i":{"x":0.58,"y":1},"s":[10.78,20.04],"t":0},{"o":{"x":0.65,"y":0},"i":{"x":0.35,"y":0},"s":[11.59,18.81],"t":18},{"o":{"x":0,"y":0},"i":{"x":0.58,"y":1},"s":[10.02,22.22],"t":24},{"s":[10.78,20.04],"t":30}]},"s":{"a":1,"k":[{"o":{"x":0,"y":0},"i":{"x":0.58,"y":1},"s":[100,100],"t":0},{"o":{"x":0.65,"y":0},"i":{"x":0.35,"y":0},"s":[100,100],"t":18},{"o":{"x":0,"y":0},"i":{"x":0.58,"y":1},"s":[100,100],"t":24},{"s":[100,100],"t":30}]},"sk":{"a":0,"k":0},"p":{"a":1,"k":[{"o":{"x":0,"y":0},"i":{"x":0.58,"y":1},"s":[254.67,1176.37],"t":0},{"o":{"x":0.65,"y":0},"i":{"x":0.35,"y":0},"s":[232.28,1181.01],"t":18},{"o":{"x":0,"y":0},"i":{"x":0.58,"y":1},"s":[276.18,1168.08],"t":24},{"s":[254.67,1176.37],"t":30}]},"r":{"a":1,"k":[{"o":{"x":0,"y":0},"i":{"x":0.58,"y":1},"s":[0],"t":0},{"o":{"x":0.65,"y":0},"i":{"x":0.35,"y":0},"s":[0],"t":18},{"o":{"x":0,"y":0},"i":{"x":0.58,"y":1},"s":[0],"t":24},{"s":[0],"t":30}]},"sa":{"a":0,"k":0},"o":{"a":1,"k":[{"o":{"x":0,"y":0},"i":{"x":0.58,"y":1},"s":[100],"t":0},{"o":{"x":0.65,"y":0},"i":{"x":0.35,"y":0},"s":[100],"t":18},{"o":{"x":0,"y":0},"i":{"x":0.58,"y":1},"s":[100],"t":24},{"s":[100],"t":30}]}},"shapes":[{"ty":"sh","bm":0,"hd":false,"nm":"","d":1,"ks":{"a":1,"k":[{"o":{"x":0,"y":0},"i":{"x":0.58,"y":1},"s":[{"c":true,"i":[[0,0],[0,0],[0,0],[0,0],[0,0]],"o":[[0,0],[0,0],[0,0],[0,0],[0,0]],"v":[[0,0],[21.57,0],[21.57,40.07],[0,40.07],[0,0]]}],"t":0},{"o":{"x":0.65,"y":0},"i":{"x":0.35,"y":0},"s":[{"c":true,"i":[[0,0],[0,0],[0,0],[0,0],[0,0]],"o":[[0,0],[0,0],[0,0],[0,0],[0,0]],"v":[[0,0],[23.17,0],[23.17,37.62],[0,37.62],[0,0]]}],"t":18},{"o":{"x":0,"y":0},"i":{"x":0.58,"y":1},"s":[{"c":true,"i":[[0,0],[0,0],[0,0],[0,0],[0,0]],"o":[[0,0],[0,0],[0,0],[0,0],[0,0]],"v":[[0,0],[20.03,0],[20.03,44.43],[0,44.43],[0,0]]}],"t":24},{"s":[{"c":true,"i":[[0,0],[0,0],[0,0],[0,0],[0,0]],"o":[[0,0],[0,0],[0,0],[0,0],[0,0]],"v":[[0,0],[21.57,0],[21.57,40.07],[0,40.07],[0,0]]}],"t":30}]}},{"ty":"fl","bm":0,"hd":false,"nm":"","c":{"a":1,"k":[{"o":{"x":0,"y":0},"i":{"x":0.58,"y":1},"s":[0.5491,0.3844,0.2236],"t":0},{"o":{"x":0.65,"y":0},"i":{"x":0.35,"y":0},"s":[0.5491,0.3844,0.2236],"t":18},{"o":{"x":0,"y":0},"i":{"x":0.58,"y":1},"s":[0.5491,0.3844,0.2236],"t":24},{"s":[0.5491,0.3844,0.2236],"t":30}]},"r":1,"o":{"a":1,"k":[{"o":{"x":0,"y":0},"i":{"x":0.58,"y":1},"s":[100],"t":0},{"o":{"x":0.65,"y":0},"i":{"x":0.35,"y":0},"s":[100],"t":18},{"o":{"x":0,"y":0},"i":{"x":0.58,"y":1},"s":[100],"t":24},{"s":[100],"t":30}]}}],"ind":4},{"ty":4,"nm":"2 / Group / Vector","sr":1,"st":0,"op":31,"ip":0,"hd":false,"ddd":0,"bm":0,"hasMask":false,"ao":0,"ks":{"a":{"a":1,"k":[{"o":{"x":0,"y":0},"i":{"x":0.58,"y":1},"s":[55.61,21.26],"t":0},{"o":{"x":0.65,"y":0},"i":{"x":0.35,"y":0},"s":[59.74,19.96],"t":18},{"o":{"x":0,"y":0},"i":{"x":0.58,"y":1},"s":[51.64,23.57],"t":24},{"s":[55.61,21.26],"t":30}]},"s":{"a":1,"k":[{"o":{"x":0,"y":0},"i":{"x":0.58,"y":1},"s":[100,100],"t":0},{"o":{"x":0.65,"y":0},"i":{"x":0.35,"y":0},"s":[100,100],"t":18},{"o":{"x":0,"y":0},"i":{"x":0.58,"y":1},"s":[100,100],"t":24},{"s":[100,100],"t":30}]},"sk":{"a":0,"k":0},"p":{"a":1,"k":[{"o":{"x":0,"y":0},"i":{"x":0.58,"y":1},"s":[857.11,1147.71],"t":0},{"o":{"x":0.65,"y":0},"i":{"x":0.35,"y":0},"s":[879.5,1154.11],"t":18},{"o":{"x":0,"y":0},"i":{"x":0.58,"y":1},"s":[835.6,1136.3],"t":24},{"s":[857.11,1147.71],"t":30}]},"r":{"a":1,"k":[{"o":{"x":0,"y":0},"i":{"x":0.58,"y":1},"s":[0],"t":0},{"o":{"x":0.65,"y":0},"i":{"x":0.35,"y":0},"s":[0],"t":18},{"o":{"x":0,"y":0},"i":{"x":0.58,"y":1},"s":[0],"t":24},{"s":[0],"t":30}]},"sa":{"a":0,"k":0},"o":{"a":1,"k":[{"o":{"x":0,"y":0},"i":{"x":0.58,"y":1},"s":[100],"t":0},{"o":{"x":0.65,"y":0},"i":{"x":0.35,"y":0},"s":[100],"t":18},{"o":{"x":0,"y":0},"i":{"x":0.58,"y":1},"s":[100],"t":24},{"s":[100],"t":30}]}},"shapes":[{"ty":"sh","bm":0,"hd":false,"nm":"","d":1,"ks":{"a":1,"k":[{"o":{"x":0,"y":0},"i":{"x":0.58,"y":1},"s":[{"c":true,"i":[[0,0],[-0.53,-2.15],[-12,48.03],[-0.47,2.18],[31.38,21.26]],"o":[[0.47,2.18],[11.99,48.03],[0.54,-2.15],[-31.39,21.26],[0,0]],"v":[[0,0],[1.51,6.49],[109.7,6.49],[111.21,0],[0,0]]}],"t":0},{"o":{"x":0.65,"y":0},"i":{"x":0.35,"y":0},"s":[{"c":true,"i":[[0,0],[-0.57,-2.02],[-12.89,45.1],[-0.5,2.05],[33.71,19.96]],"o":[[0.5,2.05],[12.88,45.1],[0.58,-2.02],[-33.72,19.96],[0,0]],"v":[[0,0],[1.62,6.09],[117.86,6.09],[119.48,0],[0,0]]}],"t":18},{"o":{"x":0,"y":0},"i":{"x":0.58,"y":1},"s":[{"c":true,"i":[[0,0],[-0.49,-2.38],[-11.14,53.26],[-0.44,2.42],[29.14,23.58]],"o":[[0.44,2.42],[11.13,53.26],[0.5,-2.38],[-29.15,23.58],[0,0]],"v":[[0,0],[1.4,7.2],[101.87,7.2],[103.27,0],[0,0]]}],"t":24},{"s":[{"c":true,"i":[[0,0],[-0.53,-2.15],[-12,48.03],[-0.47,2.18],[31.38,21.26]],"o":[[0.47,2.18],[11.99,48.03],[0.54,-2.15],[-31.39,21.26],[0,0]],"v":[[0,0],[1.51,6.49],[109.7,6.49],[111.21,0],[0,0]]}],"t":30}]}},{"ty":"fl","bm":0,"hd":false,"nm":"","c":{"a":1,"k":[{"o":{"x":0,"y":0},"i":{"x":0.58,"y":1},"s":[0.0236,0.4785,0.3804],"t":0},{"o":{"x":0.65,"y":0},"i":{"x":0.35,"y":0},"s":[0.0236,0.4785,0.3804],"t":18},{"o":{"x":0,"y":0},"i":{"x":0.58,"y":1},"s":[0.0236,0.4785,0.3804],"t":24},{"s":[0.0236,0.4785,0.3804],"t":30}]},"r":1,"o":{"a":1,"k":[{"o":{"x":0,"y":0},"i":{"x":0.58,"y":1},"s":[100],"t":0},{"o":{"x":0.65,"y":0},"i":{"x":0.35,"y":0},"s":[100],"t":18},{"o":{"x":0,"y":0},"i":{"x":0.58,"y":1},"s":[100],"t":24},{"s":[100],"t":30}]}}],"ind":5},{"ty":4,"nm":"2 / Group / Vector","sr":1,"st":0,"op":31,"ip":0,"hd":false,"ddd":0,"bm":0,"hasMask":false,"ao":0,"ks":{"a":{"a":1,"k":[{"o":{"x":0,"y":0},"i":{"x":0.58,"y":1},"s":[60.79,121.18],"t":0},{"o":{"x":0.65,"y":0},"i":{"x":0.35,"y":0},"s":[65.3,113.78],"t":18},{"o":{"x":0,"y":0},"i":{"x":0.58,"y":1},"s":[56.45,134.38],"t":24},{"s":[60.79,121.18],"t":30}]},"s":{"a":1,"k":[{"o":{"x":0,"y":0},"i":{"x":0.58,"y":1},"s":[100,100],"t":0},{"o":{"x":0.65,"y":0},"i":{"x":0.35,"y":0},"s":[100,100],"t":18},{"o":{"x":0,"y":0},"i":{"x":0.58,"y":1},"s":[100,100],"t":24},{"s":[100,100],"t":30}]},"sk":{"a":0,"k":0},"p":{"a":1,"k":[{"o":{"x":0,"y":0},"i":{"x":0.58,"y":1},"s":[857.12,1047.77],"t":0},{"o":{"x":0.65,"y":0},"i":{"x":0.35,"y":0},"s":[879.51,1060.28],"t":18},{"o":{"x":0,"y":0},"i":{"x":0.58,"y":1},"s":[835.61,1025.48],"t":24},{"s":[857.12,1047.77],"t":30}]},"r":{"a":1,"k":[{"o":{"x":0,"y":0},"i":{"x":0.58,"y":1},"s":[0],"t":0},{"o":{"x":0.65,"y":0},"i":{"x":0.35,"y":0},"s":[0],"t":18},{"o":{"x":0,"y":0},"i":{"x":0.58,"y":1},"s":[0],"t":24},{"s":[0],"t":30}]},"sa":{"a":0,"k":0},"o":{"a":1,"k":[{"o":{"x":0,"y":0},"i":{"x":0.58,"y":1},"s":[100],"t":0},{"o":{"x":0.65,"y":0},"i":{"x":0.35,"y":0},"s":[100],"t":18},{"o":{"x":0,"y":0},"i":{"x":0.58,"y":1},"s":[100],"t":24},{"s":[100],"t":30}]}},"shapes":[{"ty":"sh","bm":0,"hd":false,"nm":"","d":1,"ks":{"a":1,"k":[{"o":{"x":0,"y":0},"i":{"x":0.58,"y":1},"s":[{"c":true,"i":[[0,0],[-4.36,-17.44],[-12,48.03],[0,19.03],[37.21,36.75],[0,-60.52],[0,0]],"o":[[0,19.03],[11.99,48.03],[4.35,-17.44],[0,-60.51],[-37.21,36.74],[0,0],[0,0]],"v":[[0,151.46],[6.69,206.34],[114.88,206.34],[121.57,151.46],[60.79,0],[0.01,151.46],[0,151.46]]}],"t":0},{"o":{"x":0.65,"y":0},"i":{"x":0.35,"y":0},"s":[{"c":true,"i":[[0,0],[-4.68,-16.37],[-12.89,45.1],[0,17.87],[39.98,34.5],[0,-56.82],[0,0]],"o":[[0,17.87],[12.88,45.1],[4.67,-16.37],[0,-56.81],[-39.98,34.5],[0,0],[0,0]],"v":[[0,142.21],[7.19,193.73],[123.42,193.73],[130.61,142.21],[65.31,0],[0.01,142.21],[0,142.21]]}],"t":18},{"o":{"x":0,"y":0},"i":{"x":0.58,"y":1},"s":[{"c":true,"i":[[0,0],[-4.05,-19.34],[-11.14,53.26],[0,21.1],[34.55,40.75],[0,-67.11],[0,0]],"o":[[0,21.1],[11.13,53.26],[4.04,-19.34],[0,-67.1],[-34.55,40.74],[0,0],[0,0]],"v":[[0,167.95],[6.21,228.81],[106.68,228.81],[112.89,167.95],[56.45,0],[0.01,167.95],[0,167.95]]}],"t":24},{"s":[{"c":true,"i":[[0,0],[-4.36,-17.44],[-12,48.03],[0,19.03],[37.21,36.75],[0,-60.52],[0,0]],"o":[[0,19.03],[11.99,48.03],[4.35,-17.44],[0,-60.51],[-37.21,36.74],[0,0],[0,0]],"v":[[0,151.46],[6.69,206.34],[114.88,206.34],[121.57,151.46],[60.79,0],[0.01,151.46],[0,151.46]]}],"t":30}]}},{"ty":"fl","bm":0,"hd":false,"nm":"","c":{"a":1,"k":[{"o":{"x":0,"y":0},"i":{"x":0.58,"y":1},"s":[0.0353,0.553,0.451],"t":0},{"o":{"x":0.65,"y":0},"i":{"x":0.35,"y":0},"s":[0.0353,0.553,0.451],"t":18},{"o":{"x":0,"y":0},"i":{"x":0.58,"y":1},"s":[0.0353,0.553,0.451],"t":24},{"s":[0.0353,0.553,0.451],"t":30}]},"r":1,"o":{"a":1,"k":[{"o":{"x":0,"y":0},"i":{"x":0.58,"y":1},"s":[100],"t":0},{"o":{"x":0.65,"y":0},"i":{"x":0.35,"y":0},"s":[100],"t":18},{"o":{"x":0,"y":0},"i":{"x":0.58,"y":1},"s":[100],"t":24},{"s":[100],"t":30}]}}],"ind":6},{"ty":4,"nm":"2 / Group / Vector","sr":1,"st":0,"op":31,"ip":0,"hd":false,"ddd":0,"bm":0,"hasMask":false,"ao":0,"ks":{"a":{"a":1,"k":[{"o":{"x":0,"y":0},"i":{"x":0.58,"y":1},"s":[61.09,20.52],"t":0},{"o":{"x":0.65,"y":0},"i":{"x":0.35,"y":0},"s":[65.63,19.27],"t":18},{"o":{"x":0,"y":0},"i":{"x":0.58,"y":1},"s":[56.73,22.76],"t":24},{"s":[61.09,20.52],"t":30}]},"s":{"a":1,"k":[{"o":{"x":0,"y":0},"i":{"x":0.58,"y":1},"s":[100,100],"t":0},{"o":{"x":0.65,"y":0},"i":{"x":0.35,"y":0},"s":[100,100],"t":18},{"o":{"x":0,"y":0},"i":{"x":0.58,"y":1},"s":[100,100],"t":24},{"s":[100,100],"t":30}]},"sk":{"a":0,"k":0},"p":{"a":1,"k":[{"o":{"x":0,"y":0},"i":{"x":0.58,"y":1},"s":[857.1,1206.29],"t":0},{"o":{"x":0.65,"y":0},"i":{"x":0.35,"y":0},"s":[879.5,1209.11],"t":18},{"o":{"x":0,"y":0},"i":{"x":0.58,"y":1},"s":[835.59,1201.27],"t":24},{"s":[857.1,1206.29],"t":30}]},"r":{"a":1,"k":[{"o":{"x":0,"y":0},"i":{"x":0.58,"y":1},"s":[0],"t":0},{"o":{"x":0.65,"y":0},"i":{"x":0.35,"y":0},"s":[0],"t":18},{"o":{"x":0,"y":0},"i":{"x":0.58,"y":1},"s":[0],"t":24},{"s":[0],"t":30}]},"sa":{"a":0,"k":0},"o":{"a":1,"k":[{"o":{"x":0,"y":0},"i":{"x":0.58,"y":1},"s":[100],"t":0},{"o":{"x":0.65,"y":0},"i":{"x":0.35,"y":0},"s":[100],"t":18},{"o":{"x":0,"y":0},"i":{"x":0.58,"y":1},"s":[100],"t":24},{"s":[100],"t":30}]}},"shapes":[{"ty":"sh","bm":0,"hd":false,"nm":"","d":1,"ks":{"a":1,"k":[{"o":{"x":0,"y":0},"i":{"x":0.58,"y":1},"s":[{"c":true,"i":[[0,0],[0,0],[0,0],[0,0],[0,0]],"o":[[0,0],[0,0],[0,0],[0,0],[0,0]],"v":[[0,0],[122.18,0],[122.18,41.05],[0,41.05],[0,0]]}],"t":0},{"o":{"x":0.65,"y":0},"i":{"x":0.35,"y":0},"s":[{"c":true,"i":[[0,0],[0,0],[0,0],[0,0],[0,0]],"o":[[0,0],[0,0],[0,0],[0,0],[0,0]],"v":[[0,0],[131.26,0],[131.26,38.54],[0,38.54],[0,0]]}],"t":18},{"o":{"x":0,"y":0},"i":{"x":0.58,"y":1},"s":[{"c":true,"i":[[0,0],[0,0],[0,0],[0,0],[0,0]],"o":[[0,0],[0,0],[0,0],[0,0],[0,0]],"v":[[0,0],[113.46,0],[113.46,45.52],[0,45.52],[0,0]]}],"t":24},{"s":[{"c":true,"i":[[0,0],[0,0],[0,0],[0,0],[0,0]],"o":[[0,0],[0,0],[0,0],[0,0],[0,0]],"v":[[0,0],[122.18,0],[122.18,41.05],[0,41.05],[0,0]]}],"t":30}]}},{"ty":"fl","bm":0,"hd":false,"nm":"","c":{"a":1,"k":[{"o":{"x":0,"y":0},"i":{"x":0.58,"y":1},"s":[0.7804,0.7804,0.851],"t":0},{"o":{"x":0.65,"y":0},"i":{"x":0.35,"y":0},"s":[0.7804,0.7804,0.851],"t":18},{"o":{"x":0,"y":0},"i":{"x":0.58,"y":1},"s":[0.7804,0.7804,0.851],"t":24},{"s":[0.7804,0.7804,0.851],"t":30}]},"r":1,"o":{"a":1,"k":[{"o":{"x":0,"y":0},"i":{"x":0.58,"y":1},"s":[100],"t":0},{"o":{"x":0.65,"y":0},"i":{"x":0.35,"y":0},"s":[100],"t":18},{"o":{"x":0,"y":0},"i":{"x":0.58,"y":1},"s":[100],"t":24},{"s":[100],"t":30}]}}],"ind":7},{"ty":4,"nm":"2 / Group / Vector","sr":1,"st":0,"op":31,"ip":0,"hd":false,"ddd":0,"bm":0,"hasMask":false,"ao":0,"ks":{"a":{"a":1,"k":[{"o":{"x":0,"y":0},"i":{"x":0.58,"y":1},"s":[10.79,20.04],"t":0},{"o":{"x":0.65,"y":0},"i":{"x":0.35,"y":0},"s":[11.59,18.81],"t":18},{"o":{"x":0,"y":0},"i":{"x":0.58,"y":1},"s":[10.02,22.22],"t":24},{"s":[10.79,20.04],"t":30}]},"s":{"a":1,"k":[{"o":{"x":0,"y":0},"i":{"x":0.58,"y":1},"s":[100,100],"t":0},{"o":{"x":0.65,"y":0},"i":{"x":0.35,"y":0},"s":[100,100],"t":18},{"o":{"x":0,"y":0},"i":{"x":0.58,"y":1},"s":[100,100],"t":24},{"s":[100,100],"t":30}]},"sk":{"a":0,"k":0},"p":{"a":1,"k":[{"o":{"x":0,"y":0},"i":{"x":0.58,"y":1},"s":[857.11,1176.37],"t":0},{"o":{"x":0.65,"y":0},"i":{"x":0.35,"y":0},"s":[879.5,1181.01],"t":18},{"o":{"x":0,"y":0},"i":{"x":0.58,"y":1},"s":[835.6,1168.08],"t":24},{"s":[857.11,1176.37],"t":30}]},"r":{"a":1,"k":[{"o":{"x":0,"y":0},"i":{"x":0.58,"y":1},"s":[0],"t":0},{"o":{"x":0.65,"y":0},"i":{"x":0.35,"y":0},"s":[0],"t":18},{"o":{"x":0,"y":0},"i":{"x":0.58,"y":1},"s":[0],"t":24},{"s":[0],"t":30}]},"sa":{"a":0,"k":0},"o":{"a":1,"k":[{"o":{"x":0,"y":0},"i":{"x":0.58,"y":1},"s":[100],"t":0},{"o":{"x":0.65,"y":0},"i":{"x":0.35,"y":0},"s":[100],"t":18},{"o":{"x":0,"y":0},"i":{"x":0.58,"y":1},"s":[100],"t":24},{"s":[100],"t":30}]}},"shapes":[{"ty":"sh","bm":0,"hd":false,"nm":"","d":1,"ks":{"a":1,"k":[{"o":{"x":0,"y":0},"i":{"x":0.58,"y":1},"s":[{"c":true,"i":[[0,0],[0,0],[0,0],[0,0],[0,0]],"o":[[0,0],[0,0],[0,0],[0,0],[0,0]],"v":[[0,0],[21.57,0],[21.57,40.07],[0,40.07],[0,0]]}],"t":0},{"o":{"x":0.65,"y":0},"i":{"x":0.35,"y":0},"s":[{"c":true,"i":[[0,0],[0,0],[0,0],[0,0],[0,0]],"o":[[0,0],[0,0],[0,0],[0,0],[0,0]],"v":[[0,0],[23.17,0],[23.17,37.62],[0,37.62],[0,0]]}],"t":18},{"o":{"x":0,"y":0},"i":{"x":0.58,"y":1},"s":[{"c":true,"i":[[0,0],[0,0],[0,0],[0,0],[0,0]],"o":[[0,0],[0,0],[0,0],[0,0],[0,0]],"v":[[0,0],[20.03,0],[20.03,44.43],[0,44.43],[0,0]]}],"t":24},{"s":[{"c":true,"i":[[0,0],[0,0],[0,0],[0,0],[0,0]],"o":[[0,0],[0,0],[0,0],[0,0],[0,0]],"v":[[0,0],[21.57,0],[21.57,40.07],[0,40.07],[0,0]]}],"t":30}]}},{"ty":"fl","bm":0,"hd":false,"nm":"","c":{"a":1,"k":[{"o":{"x":0,"y":0},"i":{"x":0.58,"y":1},"s":[0.5491,0.3844,0.2236],"t":0},{"o":{"x":0.65,"y":0},"i":{"x":0.35,"y":0},"s":[0.5491,0.3844,0.2236],"t":18},{"o":{"x":0,"y":0},"i":{"x":0.58,"y":1},"s":[0.5491,0.3844,0.2236],"t":24},{"s":[0.5491,0.3844,0.2236],"t":30}]},"r":1,"o":{"a":1,"k":[{"o":{"x":0,"y":0},"i":{"x":0.58,"y":1},"s":[100],"t":0},{"o":{"x":0.65,"y":0},"i":{"x":0.35,"y":0},"s":[100],"t":18},{"o":{"x":0,"y":0},"i":{"x":0.58,"y":1},"s":[100],"t":24},{"s":[100],"t":30}]}}],"ind":8},{"ty":4,"nm":"2 / Vector","sr":1,"st":0,"op":31,"ip":0,"hd":false,"ddd":0,"bm":0,"hasMask":false,"ao":0,"ks":{"a":{"a":1,"k":[{"o":{"x":0,"y":0},"i":{"x":0.58,"y":1},"s":[382.23,12.64],"t":0},{"o":{"x":0.65,"y":0},"i":{"x":0.35,"y":0},"s":[410.64,11.87],"t":18},{"o":{"x":0,"y":0},"i":{"x":0.58,"y":1},"s":[354.94,14.02],"t":24},{"s":[382.23,12.64],"t":30}]},"s":{"a":1,"k":[{"o":{"x":0,"y":0},"i":{"x":0.58,"y":1},"s":[100,100],"t":0},{"o":{"x":0.65,"y":0},"i":{"x":0.35,"y":0},"s":[100,100],"t":18},{"o":{"x":0,"y":0},"i":{"x":0.58,"y":1},"s":[100,100],"t":24},{"s":[100,100],"t":30}]},"sk":{"a":0,"k":0},"p":{"a":1,"k":[{"o":{"x":0,"y":0},"i":{"x":0.58,"y":1},"s":[556.23,1239.46],"t":0},{"o":{"x":0.65,"y":0},"i":{"x":0.35,"y":0},"s":[556.25,1240.25],"t":18},{"o":{"x":0,"y":0},"i":{"x":0.58,"y":1},"s":[556.2,1238.05],"t":24},{"s":[556.23,1239.46],"t":30}]},"r":{"a":1,"k":[{"o":{"x":0,"y":0},"i":{"x":0.58,"y":1},"s":[0],"t":0},{"o":{"x":0.65,"y":0},"i":{"x":0.35,"y":0},"s":[0],"t":18},{"o":{"x":0,"y":0},"i":{"x":0.58,"y":1},"s":[0],"t":24},{"s":[0],"t":30}]},"sa":{"a":0,"k":0},"o":{"a":1,"k":[{"o":{"x":0,"y":0},"i":{"x":0.58,"y":1},"s":[100],"t":0},{"o":{"x":0.65,"y":0},"i":{"x":0.35,"y":0},"s":[100],"t":18},{"o":{"x":0,"y":0},"i":{"x":0.58,"y":1},"s":[100],"t":24},{"s":[100],"t":30}]}},"shapes":[{"ty":"sh","bm":0,"hd":false,"nm":"","d":1,"ks":{"a":1,"k":[{"o":{"x":0,"y":0},"i":{"x":0.58,"y":1},"s":[{"c":true,"i":[[0,0],[0,0],[0,-6.28],[0,0],[6.28,0],[0,0],[0,6.28],[0,0],[-6.28,0]],"o":[[0,0],[6.28,0],[0,0],[0,6.28],[0,0],[-6.28,0],[0,0],[0,-6.28],[0,0]],"v":[[11.37,0],[753.08,0],[764.45,11.37],[764.45,13.91],[753.08,25.28],[11.37,25.28],[0,13.91],[0,11.37],[11.37,0]]}],"t":0},{"o":{"x":0.65,"y":0},"i":{"x":0.35,"y":0},"s":[{"c":true,"i":[[0,0],[0,0],[0,-5.9],[0,0],[6.75,0],[0,0],[0,5.9],[0,0],[-6.75,0]],"o":[[0,0],[6.75,0],[0,0],[0,5.9],[0,0],[-6.75,0],[0,0],[0,-5.9],[0,0]],"v":[[12.22,0],[809.07,0],[821.29,10.68],[821.29,13.06],[809.07,23.74],[12.22,23.74],[0,13.06],[0,10.68],[12.22,0]]}],"t":18},{"o":{"x":0,"y":0},"i":{"x":0.58,"y":1},"s":[{"c":true,"i":[[0,0],[0,0],[0,-6.96],[0,0],[5.83,0],[0,0],[0,6.96],[0,0],[-5.83,0]],"o":[[0,0],[5.83,0],[0,0],[0,6.96],[0,0],[-5.83,0],[0,0],[0,-6.96],[0,0]],"v":[[10.56,0],[699.31,0],[709.87,12.61],[709.87,15.42],[699.31,28.03],[10.56,28.03],[0,15.42],[0,12.61],[10.56,0]]}],"t":24},{"s":[{"c":true,"i":[[0,0],[0,0],[0,-6.28],[0,0],[6.28,0],[0,0],[0,6.28],[0,0],[-6.28,0]],"o":[[0,0],[6.28,0],[0,0],[0,6.28],[0,0],[-6.28,0],[0,0],[0,-6.28],[0,0]],"v":[[11.37,0],[753.08,0],[764.45,11.37],[764.45,13.91],[753.08,25.28],[11.37,25.28],[0,13.91],[0,11.37],[11.37,0]]}],"t":30}]}},{"ty":"fl","bm":0,"hd":false,"nm":"","c":{"a":1,"k":[{"o":{"x":0,"y":0},"i":{"x":0.58,"y":1},"s":[0.0196,0.3804,0.3059],"t":0},{"o":{"x":0.65,"y":0},"i":{"x":0.35,"y":0},"s":[0.0196,0.3804,0.3059],"t":18},{"o":{"x":0,"y":0},"i":{"x":0.58,"y":1},"s":[0.0196,0.3804,0.3059],"t":24},{"s":[0.0196,0.3804,0.3059],"t":30}]},"r":1,"o":{"a":1,"k":[{"o":{"x":0,"y":0},"i":{"x":0.58,"y":1},"s":[100],"t":0},{"o":{"x":0.65,"y":0},"i":{"x":0.35,"y":0},"s":[100],"t":18},{"o":{"x":0,"y":0},"i":{"x":0.58,"y":1},"s":[100],"t":24},{"s":[100],"t":30}]}}],"ind":9},{"ty":4,"nm":"2 / Group / Vector","sr":1,"st":0,"op":31,"ip":0,"hd":false,"ddd":0,"bm":0,"hasMask":false,"ao":0,"ks":{"a":{"a":1,"k":[{"o":{"x":0,"y":0},"i":{"x":0.58,"y":1},"s":[22.35,1.9],"t":0},{"o":{"x":0.65,"y":0},"i":{"x":0.35,"y":0},"s":[24.01,1.78],"t":18},{"o":{"x":0,"y":0},"i":{"x":0.58,"y":1},"s":[20.75,2.11],"t":24},{"s":[22.35,1.9],"t":30}]},"s":{"a":1,"k":[{"o":{"x":0,"y":0},"i":{"x":0.58,"y":1},"s":[100,100],"t":0},{"o":{"x":0.65,"y":0},"i":{"x":0.35,"y":0},"s":[100,100],"t":18},{"o":{"x":0,"y":0},"i":{"x":0.58,"y":1},"s":[100,100],"t":24},{"s":[100,100],"t":30}]},"sk":{"a":0,"k":0},"p":{"a":1,"k":[{"o":{"x":0,"y":0},"i":{"x":0.58,"y":1},"s":[382.9,971.92],"t":0},{"o":{"x":0.65,"y":0},"i":{"x":0.35,"y":0},"s":[370.04,989.06],"t":18},{"o":{"x":0,"y":0},"i":{"x":0.58,"y":1},"s":[395.25,941.37],"t":24},{"s":[382.9,971.92],"t":30}]},"r":{"a":1,"k":[{"o":{"x":0,"y":0},"i":{"x":0.58,"y":1},"s":[0],"t":0},{"o":{"x":0.65,"y":0},"i":{"x":0.35,"y":0},"s":[0],"t":18},{"o":{"x":0,"y":0},"i":{"x":0.58,"y":1},"s":[0],"t":24},{"s":[0],"t":30}]},"sa":{"a":0,"k":0},"o":{"a":1,"k":[{"o":{"x":0,"y":0},"i":{"x":0.58,"y":1},"s":[100],"t":0},{"o":{"x":0.65,"y":0},"i":{"x":0.35,"y":0},"s":[100],"t":18},{"o":{"x":0,"y":0},"i":{"x":0.58,"y":1},"s":[100],"t":24},{"s":[100],"t":30}]}},"shapes":[{"ty":"sh","bm":0,"hd":false,"nm":"","d":1,"ks":{"a":1,"k":[{"o":{"x":0,"y":0},"i":{"x":0.58,"y":1},"s":[{"c":true,"i":[[0,0],[0,0],[0,0],[0,0],[0,0]],"o":[[0,0],[0,0],[0,0],[0,0],[0,0]],"v":[[0,0],[44.69,0],[44.69,3.8],[0,3.8],[0,0]]}],"t":0},{"o":{"x":0.65,"y":0},"i":{"x":0.35,"y":0},"s":[{"c":true,"i":[[0,0],[0,0],[0,0],[0,0],[0,0]],"o":[[0,0],[0,0],[0,0],[0,0],[0,0]],"v":[[0,0],[48.01,0],[48.01,3.57],[0,3.57],[0,0]]}],"t":18},{"o":{"x":0,"y":0},"i":{"x":0.58,"y":1},"s":[{"c":true,"i":[[0,0],[0,0],[0,0],[0,0],[0,0]],"o":[[0,0],[0,0],[0,0],[0,0],[0,0]],"v":[[0,0],[41.5,0],[41.5,4.21],[0,4.21],[0,0]]}],"t":24},{"s":[{"c":true,"i":[[0,0],[0,0],[0,0],[0,0],[0,0]],"o":[[0,0],[0,0],[0,0],[0,0],[0,0]],"v":[[0,0],[44.69,0],[44.69,3.8],[0,3.8],[0,0]]}],"t":30}]}},{"ty":"fl","bm":0,"hd":false,"nm":"","c":{"a":1,"k":[{"o":{"x":0,"y":0},"i":{"x":0.58,"y":1},"s":[0.5844,0.6157,0.6902],"t":0},{"o":{"x":0.65,"y":0},"i":{"x":0.35,"y":0},"s":[0.5844,0.6157,0.6902],"t":18},{"o":{"x":0,"y":0},"i":{"x":0.58,"y":1},"s":[0.5844,0.6157,0.6902],"t":24},{"s":[0.5844,0.6157,0.6902],"t":30}]},"r":1,"o":{"a":1,"k":[{"o":{"x":0,"y":0},"i":{"x":0.58,"y":1},"s":[100],"t":0},{"o":{"x":0.65,"y":0},"i":{"x":0.35,"y":0},"s":[100],"t":18},{"o":{"x":0,"y":0},"i":{"x":0.58,"y":1},"s":[100],"t":24},{"s":[100],"t":30}]}}],"ind":10},{"ty":4,"nm":"2 / Group / Vector","sr":1,"st":0,"op":31,"ip":0,"hd":false,"ddd":0,"bm":0,"hasMask":false,"ao":0,"ks":{"a":{"a":1,"k":[{"o":{"x":0,"y":0},"i":{"x":0.58,"y":1},"s":[8.67,0.97],"t":0},{"o":{"x":0.65,"y":0},"i":{"x":0.35,"y":0},"s":[9.32,0.91],"t":18},{"o":{"x":0,"y":0},"i":{"x":0.58,"y":1},"s":[8.06,1.08],"t":24},{"s":[8.67,0.97],"t":30}]},"s":{"a":1,"k":[{"o":{"x":0,"y":0},"i":{"x":0.58,"y":1},"s":[100,100],"t":0},{"o":{"x":0.65,"y":0},"i":{"x":0.35,"y":0},"s":[100,100],"t":18},{"o":{"x":0,"y":0},"i":{"x":0.58,"y":1},"s":[100,100],"t":24},{"s":[100,100],"t":30}]},"sk":{"a":0,"k":0},"p":{"a":1,"k":[{"o":{"x":0,"y":0},"i":{"x":0.58,"y":1},"s":[396.58,1007],"t":0},{"o":{"x":0.65,"y":0},"i":{"x":0.35,"y":0},"s":[384.74,1021.99],"t":18},{"o":{"x":0,"y":0},"i":{"x":0.58,"y":1},"s":[407.96,980.27],"t":24},{"s":[396.58,1007],"t":30}]},"r":{"a":1,"k":[{"o":{"x":0,"y":0},"i":{"x":0.58,"y":1},"s":[0],"t":0},{"o":{"x":0.65,"y":0},"i":{"x":0.35,"y":0},"s":[0],"t":18},{"o":{"x":0,"y":0},"i":{"x":0.58,"y":1},"s":[0],"t":24},{"s":[0],"t":30}]},"sa":{"a":0,"k":0},"o":{"a":1,"k":[{"o":{"x":0,"y":0},"i":{"x":0.58,"y":1},"s":[100],"t":0},{"o":{"x":0.65,"y":0},"i":{"x":0.35,"y":0},"s":[100],"t":18},{"o":{"x":0,"y":0},"i":{"x":0.58,"y":1},"s":[100],"t":24},{"s":[100],"t":30}]}},"shapes":[{"ty":"sh","bm":0,"hd":false,"nm":"","d":1,"ks":{"a":1,"k":[{"o":{"x":0,"y":0},"i":{"x":0.58,"y":1},"s":[{"c":true,"i":[[0,0],[0,0],[0,0],[0,0],[0,0]],"o":[[0,0],[0,0],[0,0],[0,0],[0,0]],"v":[[0,0],[17.35,0],[17.35,1.94],[0,1.94],[0,0]]}],"t":0},{"o":{"x":0.65,"y":0},"i":{"x":0.35,"y":0},"s":[{"c":true,"i":[[0,0],[0,0],[0,0],[0,0],[0,0]],"o":[[0,0],[0,0],[0,0],[0,0],[0,0]],"v":[[0,0],[18.64,0],[18.64,1.82],[0,1.82],[0,0]]}],"t":18},{"o":{"x":0,"y":0},"i":{"x":0.58,"y":1},"s":[{"c":true,"i":[[0,0],[0,0],[0,0],[0,0],[0,0]],"o":[[0,0],[0,0],[0,0],[0,0],[0,0]],"v":[[0,0],[16.11,0],[16.11,2.15],[0,2.15],[0,0]]}],"t":24},{"s":[{"c":true,"i":[[0,0],[0,0],[0,0],[0,0],[0,0]],"o":[[0,0],[0,0],[0,0],[0,0],[0,0]],"v":[[0,0],[17.35,0],[17.35,1.94],[0,1.94],[0,0]]}],"t":30}]}},{"ty":"fl","bm":0,"hd":false,"nm":"","c":{"a":1,"k":[{"o":{"x":0,"y":0},"i":{"x":0.58,"y":1},"s":[0.5844,0.6157,0.6902],"t":0},{"o":{"x":0.65,"y":0},"i":{"x":0.35,"y":0},"s":[0.5844,0.6157,0.6902],"t":18},{"o":{"x":0,"y":0},"i":{"x":0.58,"y":1},"s":[0.5844,0.6157,0.6902],"t":24},{"s":[0.5844,0.6157,0.6902],"t":30}]},"r":1,"o":{"a":1,"k":[{"o":{"x":0,"y":0},"i":{"x":0.58,"y":1},"s":[100],"t":0},{"o":{"x":0.65,"y":0},"i":{"x":0.35,"y":0},"s":[100],"t":18},{"o":{"x":0,"y":0},"i":{"x":0.58,"y":1},"s":[100],"t":24},{"s":[100],"t":30}]}}],"ind":11},{"ty":4,"nm":"2 / Group / Vector","sr":1,"st":0,"op":31,"ip":0,"hd":false,"ddd":0,"bm":0,"hasMask":false,"ao":0,"ks":{"a":{"a":1,"k":[{"o":{"x":0,"y":0},"i":{"x":0.58,"y":1},"s":[16.22,1.9],"t":0},{"o":{"x":0.65,"y":0},"i":{"x":0.35,"y":0},"s":[17.43,1.78],"t":18},{"o":{"x":0,"y":0},"i":{"x":0.58,"y":1},"s":[15.07,2.11],"t":24},{"s":[16.22,1.9],"t":30}]},"s":{"a":1,"k":[{"o":{"x":0,"y":0},"i":{"x":0.58,"y":1},"s":[100,100],"t":0},{"o":{"x":0.65,"y":0},"i":{"x":0.35,"y":0},"s":[100,100],"t":18},{"o":{"x":0,"y":0},"i":{"x":0.58,"y":1},"s":[100,100],"t":24},{"s":[100,100],"t":30}]},"sk":{"a":0,"k":0},"p":{"a":1,"k":[{"o":{"x":0,"y":0},"i":{"x":0.58,"y":1},"s":[383.94,993.25],"t":0},{"o":{"x":0.65,"y":0},"i":{"x":0.35,"y":0},"s":[371.15,1009.08],"t":18},{"o":{"x":0,"y":0},"i":{"x":0.58,"y":1},"s":[396.21,965.02],"t":24},{"s":[383.94,993.25],"t":30}]},"r":{"a":1,"k":[{"o":{"x":0,"y":0},"i":{"x":0.58,"y":1},"s":[0],"t":0},{"o":{"x":0.65,"y":0},"i":{"x":0.35,"y":0},"s":[0],"t":18},{"o":{"x":0,"y":0},"i":{"x":0.58,"y":1},"s":[0],"t":24},{"s":[0],"t":30}]},"sa":{"a":0,"k":0},"o":{"a":1,"k":[{"o":{"x":0,"y":0},"i":{"x":0.58,"y":1},"s":[100],"t":0},{"o":{"x":0.65,"y":0},"i":{"x":0.35,"y":0},"s":[100],"t":18},{"o":{"x":0,"y":0},"i":{"x":0.58,"y":1},"s":[100],"t":24},{"s":[100],"t":30}]}},"shapes":[{"ty":"sh","bm":0,"hd":false,"nm":"","d":1,"ks":{"a":1,"k":[{"o":{"x":0,"y":0},"i":{"x":0.58,"y":1},"s":[{"c":true,"i":[[0,0],[0,0],[0,0],[0,0],[0,0]],"o":[[0,0],[0,0],[0,0],[0,0],[0,0]],"v":[[0,0],[32.45,0],[32.45,3.8],[0,3.8],[0,0]]}],"t":0},{"o":{"x":0.65,"y":0},"i":{"x":0.35,"y":0},"s":[{"c":true,"i":[[0,0],[0,0],[0,0],[0,0],[0,0]],"o":[[0,0],[0,0],[0,0],[0,0],[0,0]],"v":[[0,0],[34.86,0],[34.86,3.57],[0,3.57],[0,0]]}],"t":18},{"o":{"x":0,"y":0},"i":{"x":0.58,"y":1},"s":[{"c":true,"i":[[0,0],[0,0],[0,0],[0,0],[0,0]],"o":[[0,0],[0,0],[0,0],[0,0],[0,0]],"v":[[0,0],[30.13,0],[30.13,4.21],[0,4.21],[0,0]]}],"t":24},{"s":[{"c":true,"i":[[0,0],[0,0],[0,0],[0,0],[0,0]],"o":[[0,0],[0,0],[0,0],[0,0],[0,0]],"v":[[0,0],[32.45,0],[32.45,3.8],[0,3.8],[0,0]]}],"t":30}]}},{"ty":"fl","bm":0,"hd":false,"nm":"","c":{"a":1,"k":[{"o":{"x":0,"y":0},"i":{"x":0.58,"y":1},"s":[0.5844,0.6157,0.6902],"t":0},{"o":{"x":0.65,"y":0},"i":{"x":0.35,"y":0},"s":[0.5844,0.6157,0.6902],"t":18},{"o":{"x":0,"y":0},"i":{"x":0.58,"y":1},"s":[0.5844,0.6157,0.6902],"t":24},{"s":[0.5844,0.6157,0.6902],"t":30}]},"r":1,"o":{"a":1,"k":[{"o":{"x":0,"y":0},"i":{"x":0.58,"y":1},"s":[100],"t":0},{"o":{"x":0.65,"y":0},"i":{"x":0.35,"y":0},"s":[100],"t":18},{"o":{"x":0,"y":0},"i":{"x":0.58,"y":1},"s":[100],"t":24},{"s":[100],"t":30}]}}],"ind":12},{"ty":4,"nm":"2 / Group / Vector","sr":1,"st":0,"op":31,"ip":0,"hd":false,"ddd":0,"bm":0,"hasMask":false,"ao":0,"ks":{"a":{"a":1,"k":[{"o":{"x":0,"y":0},"i":{"x":0.58,"y":1},"s":[16.23,1.9],"t":0},{"o":{"x":0.65,"y":0},"i":{"x":0.35,"y":0},"s":[17.43,1.78],"t":18},{"o":{"x":0,"y":0},"i":{"x":0.58,"y":1},"s":[15.07,2.11],"t":24},{"s":[16.23,1.9],"t":30}]},"s":{"a":1,"k":[{"o":{"x":0,"y":0},"i":{"x":0.58,"y":1},"s":[100,100],"t":0},{"o":{"x":0.65,"y":0},"i":{"x":0.35,"y":0},"s":[100,100],"t":18},{"o":{"x":0,"y":0},"i":{"x":0.58,"y":1},"s":[100,100],"t":24},{"s":[100,100],"t":30}]},"sk":{"a":0,"k":0},"p":{"a":1,"k":[{"o":{"x":0,"y":0},"i":{"x":0.58,"y":1},"s":[382.9,962],"t":0},{"o":{"x":0.65,"y":0},"i":{"x":0.35,"y":0},"s":[370.04,979.74],"t":18},{"o":{"x":0,"y":0},"i":{"x":0.58,"y":1},"s":[395.25,930.37],"t":24},{"s":[382.9,962],"t":30}]},"r":{"a":1,"k":[{"o":{"x":0,"y":0},"i":{"x":0.58,"y":1},"s":[0],"t":0},{"o":{"x":0.65,"y":0},"i":{"x":0.35,"y":0},"s":[0],"t":18},{"o":{"x":0,"y":0},"i":{"x":0.58,"y":1},"s":[0],"t":24},{"s":[0],"t":30}]},"sa":{"a":0,"k":0},"o":{"a":1,"k":[{"o":{"x":0,"y":0},"i":{"x":0.58,"y":1},"s":[100],"t":0},{"o":{"x":0.65,"y":0},"i":{"x":0.35,"y":0},"s":[100],"t":18},{"o":{"x":0,"y":0},"i":{"x":0.58,"y":1},"s":[100],"t":24},{"s":[100],"t":30}]}},"shapes":[{"ty":"sh","bm":0,"hd":false,"nm":"","d":1,"ks":{"a":1,"k":[{"o":{"x":0,"y":0},"i":{"x":0.58,"y":1},"s":[{"c":true,"i":[[0,0],[0,0],[0,0],[0,0],[0,0]],"o":[[0,0],[0,0],[0,0],[0,0],[0,0]],"v":[[0,0],[32.45,0],[32.45,3.8],[0,3.8],[0,0]]}],"t":0},{"o":{"x":0.65,"y":0},"i":{"x":0.35,"y":0},"s":[{"c":true,"i":[[0,0],[0,0],[0,0],[0,0],[0,0]],"o":[[0,0],[0,0],[0,0],[0,0],[0,0]],"v":[[0,0],[34.86,0],[34.86,3.57],[0,3.57],[0,0]]}],"t":18},{"o":{"x":0,"y":0},"i":{"x":0.58,"y":1},"s":[{"c":true,"i":[[0,0],[0,0],[0,0],[0,0],[0,0]],"o":[[0,0],[0,0],[0,0],[0,0],[0,0]],"v":[[0,0],[30.13,0],[30.13,4.21],[0,4.21],[0,0]]}],"t":24},{"s":[{"c":true,"i":[[0,0],[0,0],[0,0],[0,0],[0,0]],"o":[[0,0],[0,0],[0,0],[0,0],[0,0]],"v":[[0,0],[32.45,0],[32.45,3.8],[0,3.8],[0,0]]}],"t":30}]}},{"ty":"fl","bm":0,"hd":false,"nm":"","c":{"a":1,"k":[{"o":{"x":0,"y":0},"i":{"x":0.58,"y":1},"s":[0.5844,0.6157,0.6902],"t":0},{"o":{"x":0.65,"y":0},"i":{"x":0.35,"y":0},"s":[0.5844,0.6157,0.6902],"t":18},{"o":{"x":0,"y":0},"i":{"x":0.58,"y":1},"s":[0.5844,0.6157,0.6902],"t":24},{"s":[0.5844,0.6157,0.6902],"t":30}]},"r":1,"o":{"a":1,"k":[{"o":{"x":0,"y":0},"i":{"x":0.58,"y":1},"s":[100],"t":0},{"o":{"x":0.65,"y":0},"i":{"x":0.35,"y":0},"s":[100],"t":18},{"o":{"x":0,"y":0},"i":{"x":0.58,"y":1},"s":[100],"t":24},{"s":[100],"t":30}]}}],"ind":13},{"ty":4,"nm":"2 / Group / Vector","sr":1,"st":0,"op":31,"ip":0,"hd":false,"ddd":0,"bm":0,"hasMask":false,"ao":0,"ks":{"a":{"a":1,"k":[{"o":{"x":0,"y":0},"i":{"x":0.58,"y":1},"s":[2.46,2.46],"t":0},{"o":{"x":0.65,"y":0},"i":{"x":0.35,"y":0},"s":[2.64,2.31],"t":18},{"o":{"x":0,"y":0},"i":{"x":0.58,"y":1},"s":[2.28,2.73],"t":24},{"s":[2.46,2.46],"t":30}]},"s":{"a":1,"k":[{"o":{"x":0,"y":0},"i":{"x":0.58,"y":1},"s":[100,100],"t":0},{"o":{"x":0.65,"y":0},"i":{"x":0.35,"y":0},"s":[100,100],"t":18},{"o":{"x":0,"y":0},"i":{"x":0.58,"y":1},"s":[100,100],"t":24},{"s":[100,100],"t":30}]},"sk":{"a":0,"k":0},"p":{"a":1,"k":[{"o":{"x":0,"y":0},"i":{"x":0.58,"y":1},"s":[383.96,946.71],"t":0},{"o":{"x":0.65,"y":0},"i":{"x":0.35,"y":0},"s":[371.18,965.39],"t":18},{"o":{"x":0,"y":0},"i":{"x":0.58,"y":1},"s":[396.23,913.41],"t":24},{"s":[383.96,946.71],"t":30}]},"r":{"a":1,"k":[{"o":{"x":0,"y":0},"i":{"x":0.58,"y":1},"s":[0],"t":0},{"o":{"x":0.65,"y":0},"i":{"x":0.35,"y":0},"s":[0],"t":18},{"o":{"x":0,"y":0},"i":{"x":0.58,"y":1},"s":[0],"t":24},{"s":[0],"t":30}]},"sa":{"a":0,"k":0},"o":{"a":1,"k":[{"o":{"x":0,"y":0},"i":{"x":0.58,"y":1},"s":[100],"t":0},{"o":{"x":0.65,"y":0},"i":{"x":0.35,"y":0},"s":[100],"t":18},{"o":{"x":0,"y":0},"i":{"x":0.58,"y":1},"s":[100],"t":24},{"s":[100],"t":30}]}},"shapes":[{"ty":"sh","bm":0,"hd":false,"nm":"","d":1,"ks":{"a":1,"k":[{"o":{"x":0,"y":0},"i":{"x":0.58,"y":1},"s":[{"c":true,"i":[[0,0],[1.36,0],[0,1.36],[-1.36,0],[0,-1.36]],"o":[[0,1.36],[-1.36,0],[0,-1.36],[1.36,0],[0,0]],"v":[[4.92,2.46],[2.46,4.92],[0,2.46],[2.46,0],[4.92,2.46]]}],"t":0},{"o":{"x":0.65,"y":0},"i":{"x":0.35,"y":0},"s":[{"c":true,"i":[[0,0],[1.46,0],[0,1.28],[-1.46,0],[0,-1.28]],"o":[[0,1.28],[-1.46,0],[0,-1.28],[1.46,0],[0,0]],"v":[[5.29,2.31],[2.64,4.62],[0,2.31],[2.64,0],[5.29,2.31]]}],"t":18},{"o":{"x":0,"y":0},"i":{"x":0.58,"y":1},"s":[{"c":true,"i":[[0,0],[1.26,0],[0,1.51],[-1.26,0],[0,-1.51]],"o":[[0,1.51],[-1.26,0],[0,-1.51],[1.26,0],[0,0]],"v":[[4.57,2.73],[2.28,5.46],[0,2.73],[2.28,0],[4.57,2.73]]}],"t":24},{"s":[{"c":true,"i":[[0,0],[1.36,0],[0,1.36],[-1.36,0],[0,-1.36]],"o":[[0,1.36],[-1.36,0],[0,-1.36],[1.36,0],[0,0]],"v":[[4.92,2.46],[2.46,4.92],[0,2.46],[2.46,0],[4.92,2.46]]}],"t":30}]}},{"ty":"fl","bm":0,"hd":false,"nm":"","c":{"a":1,"k":[{"o":{"x":0,"y":0},"i":{"x":0.58,"y":1},"s":[0.1647,0.2549,0.3569],"t":0},{"o":{"x":0.65,"y":0},"i":{"x":0.35,"y":0},"s":[0.1647,0.2549,0.3569],"t":18},{"o":{"x":0,"y":0},"i":{"x":0.58,"y":1},"s":[0.1647,0.2549,0.3569],"t":24},{"s":[0.1647,0.2549,0.3569],"t":30}]},"r":1,"o":{"a":1,"k":[{"o":{"x":0,"y":0},"i":{"x":0.58,"y":1},"s":[100],"t":0},{"o":{"x":0.65,"y":0},"i":{"x":0.35,"y":0},"s":[100],"t":18},{"o":{"x":0,"y":0},"i":{"x":0.58,"y":1},"s":[100],"t":24},{"s":[100],"t":30}]}}],"ind":14},{"ty":4,"nm":"2 / Group / Vector","sr":1,"st":0,"op":31,"ip":0,"hd":false,"ddd":0,"bm":0,"hasMask":false,"ao":0,"ks":{"a":{"a":1,"k":[{"o":{"x":0,"y":0},"i":{"x":0.58,"y":1},"s":[30.18,43.83],"t":0},{"o":{"x":0.65,"y":0},"i":{"x":0.35,"y":0},"s":[32.43,41.15],"t":18},{"o":{"x":0,"y":0},"i":{"x":0.58,"y":1},"s":[28.03,48.6],"t":24},{"s":[30.18,43.83],"t":30}]},"s":{"a":1,"k":[{"o":{"x":0,"y":0},"i":{"x":0.58,"y":1},"s":[100,100],"t":0},{"o":{"x":0.65,"y":0},"i":{"x":0.35,"y":0},"s":[100,100],"t":18},{"o":{"x":0,"y":0},"i":{"x":0.58,"y":1},"s":[100,100],"t":24},{"s":[100,100],"t":30}]},"sk":{"a":0,"k":0},"p":{"a":1,"k":[{"o":{"x":0,"y":0},"i":{"x":0.58,"y":1},"s":[383.95,984.64],"t":0},{"o":{"x":0.65,"y":0},"i":{"x":0.35,"y":0},"s":[371.17,1001],"t":18},{"o":{"x":0,"y":0},"i":{"x":0.58,"y":1},"s":[396.23,955.47],"t":24},{"s":[383.95,984.64],"t":30}]},"r":{"a":1,"k":[{"o":{"x":0,"y":0},"i":{"x":0.58,"y":1},"s":[0],"t":0},{"o":{"x":0.65,"y":0},"i":{"x":0.35,"y":0},"s":[0],"t":18},{"o":{"x":0,"y":0},"i":{"x":0.58,"y":1},"s":[0],"t":24},{"s":[0],"t":30}]},"sa":{"a":0,"k":0},"o":{"a":1,"k":[{"o":{"x":0,"y":0},"i":{"x":0.58,"y":1},"s":[100],"t":0},{"o":{"x":0.65,"y":0},"i":{"x":0.35,"y":0},"s":[100],"t":18},{"o":{"x":0,"y":0},"i":{"x":0.58,"y":1},"s":[100],"t":24},{"s":[100],"t":30}]}},"shapes":[{"ty":"sh","bm":0,"hd":false,"nm":"","d":1,"ks":{"a":1,"k":[{"o":{"x":0,"y":0},"i":{"x":0.58,"y":1},"s":[{"c":true,"i":[[0,0],[0,0],[0,0],[0,0],[0,0]],"o":[[0,0],[0,0],[0,0],[0,0],[0,0]],"v":[[0,0],[60.37,0],[60.37,87.65],[0,87.65],[0,0]]}],"t":0},{"o":{"x":0.65,"y":0},"i":{"x":0.35,"y":0},"s":[{"c":true,"i":[[0,0],[0,0],[0,0],[0,0],[0,0]],"o":[[0,0],[0,0],[0,0],[0,0],[0,0]],"v":[[0,0],[64.86,0],[64.86,82.3],[0,82.3],[0,0]]}],"t":18},{"o":{"x":0,"y":0},"i":{"x":0.58,"y":1},"s":[{"c":true,"i":[[0,0],[0,0],[0,0],[0,0],[0,0]],"o":[[0,0],[0,0],[0,0],[0,0],[0,0]],"v":[[0,0],[56.06,0],[56.06,97.2],[0,97.2],[0,0]]}],"t":24},{"s":[{"c":true,"i":[[0,0],[0,0],[0,0],[0,0],[0,0]],"o":[[0,0],[0,0],[0,0],[0,0],[0,0]],"v":[[0,0],[60.37,0],[60.37,87.65],[0,87.65],[0,0]]}],"t":30}]}},{"ty":"fl","bm":0,"hd":false,"nm":"","c":{"a":1,"k":[{"o":{"x":0,"y":0},"i":{"x":0.58,"y":1},"s":[0.8863,0.8863,0.902],"t":0},{"o":{"x":0.65,"y":0},"i":{"x":0.35,"y":0},"s":[0.8863,0.8863,0.902],"t":18},{"o":{"x":0,"y":0},"i":{"x":0.58,"y":1},"s":[0.8863,0.8863,0.902],"t":24},{"s":[0.8863,0.8863,0.902],"t":30}]},"r":1,"o":{"a":1,"k":[{"o":{"x":0,"y":0},"i":{"x":0.58,"y":1},"s":[100],"t":0},{"o":{"x":0.65,"y":0},"i":{"x":0.35,"y":0},"s":[100],"t":18},{"o":{"x":0,"y":0},"i":{"x":0.58,"y":1},"s":[100],"t":24},{"s":[100],"t":30}]}}],"ind":15},{"ty":4,"nm":"2 / Group / Vector","sr":1,"st":0,"op":31,"ip":0,"hd":false,"ddd":0,"bm":0,"hasMask":false,"ao":0,"ks":{"a":{"a":1,"k":[{"o":{"x":0,"y":0},"i":{"x":0.58,"y":1},"s":[48.87,63.37],"t":0},{"o":{"x":0.65,"y":0},"i":{"x":0.35,"y":0},"s":[52.5,59.5],"t":18},{"o":{"x":0,"y":0},"i":{"x":0.58,"y":1},"s":[45.38,70.27],"t":24},{"s":[48.87,63.37],"t":30}]},"s":{"a":1,"k":[{"o":{"x":0,"y":0},"i":{"x":0.58,"y":1},"s":[100,100],"t":0},{"o":{"x":0.65,"y":0},"i":{"x":0.35,"y":0},"s":[100,100],"t":18},{"o":{"x":0,"y":0},"i":{"x":0.58,"y":1},"s":[100,100],"t":24},{"s":[100,100],"t":30}]},"sk":{"a":0,"k":0},"p":{"a":1,"k":[{"o":{"x":0,"y":0},"i":{"x":0.58,"y":1},"s":[383.95,989.97],"t":0},{"o":{"x":0.65,"y":0},"i":{"x":0.35,"y":0},"s":[371.17,1006.01],"t":18},{"o":{"x":0,"y":0},"i":{"x":0.58,"y":1},"s":[396.23,961.39],"t":24},{"s":[383.95,989.97],"t":30}]},"r":{"a":1,"k":[{"o":{"x":0,"y":0},"i":{"x":0.58,"y":1},"s":[0],"t":0},{"o":{"x":0.65,"y":0},"i":{"x":0.35,"y":0},"s":[0],"t":18},{"o":{"x":0,"y":0},"i":{"x":0.58,"y":1},"s":[0],"t":24},{"s":[0],"t":30}]},"sa":{"a":0,"k":0},"o":{"a":1,"k":[{"o":{"x":0,"y":0},"i":{"x":0.58,"y":1},"s":[100],"t":0},{"o":{"x":0.65,"y":0},"i":{"x":0.35,"y":0},"s":[100],"t":18},{"o":{"x":0,"y":0},"i":{"x":0.58,"y":1},"s":[100],"t":24},{"s":[100],"t":30}]}},"shapes":[{"ty":"sh","bm":0,"hd":false,"nm":"","d":1,"ks":{"a":1,"k":[{"o":{"x":0,"y":0},"i":{"x":0.58,"y":1},"s":[{"c":true,"i":[[0,0],[0,0],[0,0],[0,0],[0,0]],"o":[[0,0],[0,0],[0,0],[0,0],[0,0]],"v":[[0,0],[97.73,0],[97.73,126.74],[0,126.74],[0,0]]}],"t":0},{"o":{"x":0.65,"y":0},"i":{"x":0.35,"y":0},"s":[{"c":true,"i":[[0,0],[0,0],[0,0],[0,0],[0,0]],"o":[[0,0],[0,0],[0,0],[0,0],[0,0]],"v":[[0,0],[105,0],[105,119],[0,119],[0,0]]}],"t":18},{"o":{"x":0,"y":0},"i":{"x":0.58,"y":1},"s":[{"c":true,"i":[[0,0],[0,0],[0,0],[0,0],[0,0]],"o":[[0,0],[0,0],[0,0],[0,0],[0,0]],"v":[[0,0],[90.75,0],[90.75,140.54],[0,140.54],[0,0]]}],"t":24},{"s":[{"c":true,"i":[[0,0],[0,0],[0,0],[0,0],[0,0]],"o":[[0,0],[0,0],[0,0],[0,0],[0,0]],"v":[[0,0],[97.73,0],[97.73,126.74],[0,126.74],[0,0]]}],"t":30}]}},{"ty":"fl","bm":0,"hd":false,"nm":"","c":{"a":1,"k":[{"o":{"x":0,"y":0},"i":{"x":0.58,"y":1},"s":[0.5844,0.6157,0.6902],"t":0},{"o":{"x":0.65,"y":0},"i":{"x":0.35,"y":0},"s":[0.5844,0.6157,0.6902],"t":18},{"o":{"x":0,"y":0},"i":{"x":0.58,"y":1},"s":[0.5844,0.6157,0.6902],"t":24},{"s":[0.5844,0.6157,0.6902],"t":30}]},"r":1,"o":{"a":1,"k":[{"o":{"x":0,"y":0},"i":{"x":0.58,"y":1},"s":[100],"t":0},{"o":{"x":0.65,"y":0},"i":{"x":0.35,"y":0},"s":[100],"t":18},{"o":{"x":0,"y":0},"i":{"x":0.58,"y":1},"s":[100],"t":24},{"s":[100],"t":30}]}}],"ind":16},{"ty":4,"nm":"2 / Group / Vector","sr":1,"st":0,"op":31,"ip":0,"hd":false,"ddd":0,"bm":0,"hasMask":false,"ao":0,"ks":{"a":{"a":1,"k":[{"o":{"x":0,"y":0},"i":{"x":0.58,"y":1},"s":[48.72,2.83],"t":0},{"o":{"x":0.65,"y":0},"i":{"x":0.35,"y":0},"s":[52.34,2.66],"t":18},{"o":{"x":0,"y":0},"i":{"x":0.58,"y":1},"s":[45.24,3.14],"t":24},{"s":[48.72,2.83],"t":30}]},"s":{"a":1,"k":[{"o":{"x":0,"y":0},"i":{"x":0.58,"y":1},"s":[100,100],"t":0},{"o":{"x":0.65,"y":0},"i":{"x":0.35,"y":0},"s":[100,100],"t":18},{"o":{"x":0,"y":0},"i":{"x":0.58,"y":1},"s":[100,100],"t":24},{"s":[100,100],"t":30}]},"sk":{"a":0,"k":0},"p":{"a":1,"k":[{"o":{"x":0,"y":0},"i":{"x":0.58,"y":1},"s":[557.51,633.55],"t":0},{"o":{"x":0.65,"y":0},"i":{"x":0.35,"y":0},"s":[557.64,671.36],"t":18},{"o":{"x":0,"y":0},"i":{"x":0.58,"y":1},"s":[557.4,566.15],"t":24},{"s":[557.51,633.55],"t":30}]},"r":{"a":1,"k":[{"o":{"x":0,"y":0},"i":{"x":0.58,"y":1},"s":[0],"t":0},{"o":{"x":0.65,"y":0},"i":{"x":0.35,"y":0},"s":[0],"t":18},{"o":{"x":0,"y":0},"i":{"x":0.58,"y":1},"s":[0],"t":24},{"s":[0],"t":30}]},"sa":{"a":0,"k":0},"o":{"a":1,"k":[{"o":{"x":0,"y":0},"i":{"x":0.58,"y":1},"s":[100],"t":0},{"o":{"x":0.65,"y":0},"i":{"x":0.35,"y":0},"s":[100],"t":18},{"o":{"x":0,"y":0},"i":{"x":0.58,"y":1},"s":[100],"t":24},{"s":[100],"t":30}]}},"shapes":[{"ty":"sh","bm":0,"hd":false,"nm":"","d":1,"ks":{"a":1,"k":[{"o":{"x":0,"y":0},"i":{"x":0.58,"y":1},"s":[{"c":true,"i":[[0,0],[0,0],[0,0],[0,0],[0,0]],"o":[[0,0],[0,0],[0,0],[0,0],[0,0]],"v":[[0,0],[97.43,0],[97.43,5.66],[0,5.66],[0,0]]}],"t":0},{"o":{"x":0.65,"y":0},"i":{"x":0.35,"y":0},"s":[{"c":true,"i":[[0,0],[0,0],[0,0],[0,0],[0,0]],"o":[[0,0],[0,0],[0,0],[0,0],[0,0]],"v":[[0,0],[104.67,0],[104.67,5.31],[0,5.31],[0,0]]}],"t":18},{"o":{"x":0,"y":0},"i":{"x":0.58,"y":1},"s":[{"c":true,"i":[[0,0],[0,0],[0,0],[0,0],[0,0]],"o":[[0,0],[0,0],[0,0],[0,0],[0,0]],"v":[[0,0],[90.47,0],[90.47,6.28],[0,6.28],[0,0]]}],"t":24},{"s":[{"c":true,"i":[[0,0],[0,0],[0,0],[0,0],[0,0]],"o":[[0,0],[0,0],[0,0],[0,0],[0,0]],"v":[[0,0],[97.43,0],[97.43,5.66],[0,5.66],[0,0]]}],"t":30}]}},{"ty":"fl","bm":0,"hd":false,"nm":"","c":{"a":1,"k":[{"o":{"x":0,"y":0},"i":{"x":0.58,"y":1},"s":[0.0824,0.1608,0.2157],"t":0},{"o":{"x":0.65,"y":0},"i":{"x":0.35,"y":0},"s":[0.0824,0.1608,0.2157],"t":18},{"o":{"x":0,"y":0},"i":{"x":0.58,"y":1},"s":[0.0824,0.1608,0.2157],"t":24},{"s":[0.0824,0.1608,0.2157],"t":30}]},"r":1,"o":{"a":1,"k":[{"o":{"x":0,"y":0},"i":{"x":0.58,"y":1},"s":[100],"t":0},{"o":{"x":0.65,"y":0},"i":{"x":0.35,"y":0},"s":[100],"t":18},{"o":{"x":0,"y":0},"i":{"x":0.58,"y":1},"s":[100],"t":24},{"s":[100],"t":30}]}}],"ind":17},{"ty":4,"nm":"2 / Group / Vector","sr":1,"st":0,"op":31,"ip":0,"hd":false,"ddd":0,"bm":0,"hasMask":false,"ao":0,"ks":{"a":{"a":1,"k":[{"o":{"x":0,"y":0},"i":{"x":0.58,"y":1},"s":[2.83,47.07],"t":0},{"o":{"x":0.65,"y":0},"i":{"x":0.35,"y":0},"s":[3.04,44.2],"t":18},{"o":{"x":0,"y":0},"i":{"x":0.58,"y":1},"s":[2.63,52.2],"t":24},{"s":[2.83,47.07],"t":30}]},"s":{"a":1,"k":[{"o":{"x":0,"y":0},"i":{"x":0.58,"y":1},"s":[100,100],"t":0},{"o":{"x":0.65,"y":0},"i":{"x":0.35,"y":0},"s":[100,100],"t":18},{"o":{"x":0,"y":0},"i":{"x":0.58,"y":1},"s":[100,100],"t":24},{"s":[100,100],"t":30}]},"sk":{"a":0,"k":0},"p":{"a":1,"k":[{"o":{"x":0,"y":0},"i":{"x":0.58,"y":1},"s":[557.51,633.56],"t":0},{"o":{"x":0.65,"y":0},"i":{"x":0.35,"y":0},"s":[557.63,671.36],"t":18},{"o":{"x":0,"y":0},"i":{"x":0.58,"y":1},"s":[557.39,566.16],"t":24},{"s":[557.51,633.56],"t":30}]},"r":{"a":1,"k":[{"o":{"x":0,"y":0},"i":{"x":0.58,"y":1},"s":[0],"t":0},{"o":{"x":0.65,"y":0},"i":{"x":0.35,"y":0},"s":[0],"t":18},{"o":{"x":0,"y":0},"i":{"x":0.58,"y":1},"s":[0],"t":24},{"s":[0],"t":30}]},"sa":{"a":0,"k":0},"o":{"a":1,"k":[{"o":{"x":0,"y":0},"i":{"x":0.58,"y":1},"s":[100],"t":0},{"o":{"x":0.65,"y":0},"i":{"x":0.35,"y":0},"s":[100],"t":18},{"o":{"x":0,"y":0},"i":{"x":0.58,"y":1},"s":[100],"t":24},{"s":[100],"t":30}]}},"shapes":[{"ty":"sh","bm":0,"hd":false,"nm":"","d":1,"ks":{"a":1,"k":[{"o":{"x":0,"y":0},"i":{"x":0.58,"y":1},"s":[{"c":true,"i":[[0,0],[0,0],[0,0],[0,0],[0,0]],"o":[[0,0],[0,0],[0,0],[0,0],[0,0]],"v":[[0,0],[5.66,0],[5.66,94.15],[0,94.15],[0,0]]}],"t":0},{"o":{"x":0.65,"y":0},"i":{"x":0.35,"y":0},"s":[{"c":true,"i":[[0,0],[0,0],[0,0],[0,0],[0,0]],"o":[[0,0],[0,0],[0,0],[0,0],[0,0]],"v":[[0,0],[6.08,0],[6.08,88.4],[0,88.4],[0,0]]}],"t":18},{"o":{"x":0,"y":0},"i":{"x":0.58,"y":1},"s":[{"c":true,"i":[[0,0],[0,0],[0,0],[0,0],[0,0]],"o":[[0,0],[0,0],[0,0],[0,0],[0,0]],"v":[[0,0],[5.26,0],[5.26,104.4],[0,104.4],[0,0]]}],"t":24},{"s":[{"c":true,"i":[[0,0],[0,0],[0,0],[0,0],[0,0]],"o":[[0,0],[0,0],[0,0],[0,0],[0,0]],"v":[[0,0],[5.66,0],[5.66,94.15],[0,94.15],[0,0]]}],"t":30}]}},{"ty":"fl","bm":0,"hd":false,"nm":"","c":{"a":1,"k":[{"o":{"x":0,"y":0},"i":{"x":0.58,"y":1},"s":[0.0824,0.1608,0.2157],"t":0},{"o":{"x":0.65,"y":0},"i":{"x":0.35,"y":0},"s":[0.0824,0.1608,0.2157],"t":18},{"o":{"x":0,"y":0},"i":{"x":0.58,"y":1},"s":[0.0824,0.1608,0.2157],"t":24},{"s":[0.0824,0.1608,0.2157],"t":30}]},"r":1,"o":{"a":1,"k":[{"o":{"x":0,"y":0},"i":{"x":0.58,"y":1},"s":[100],"t":0},{"o":{"x":0.65,"y":0},"i":{"x":0.35,"y":0},"s":[100],"t":18},{"o":{"x":0,"y":0},"i":{"x":0.58,"y":1},"s":[100],"t":24},{"s":[100],"t":30}]}}],"ind":18},{"ty":4,"nm":"2 / Group / Vector","sr":1,"st":0,"op":31,"ip":0,"hd":false,"ddd":0,"bm":0,"hasMask":false,"ao":0,"ks":{"a":{"a":1,"k":[{"o":{"x":0,"y":0},"i":{"x":0.58,"y":1},"s":[161.85,267.1],"t":0},{"o":{"x":0.65,"y":0},"i":{"x":0.35,"y":0},"s":[173.89,250.78],"t":18},{"o":{"x":0,"y":0},"i":{"x":0.58,"y":1},"s":[150.3,296.19],"t":24},{"s":[161.85,267.1],"t":30}]},"s":{"a":1,"k":[{"o":{"x":0,"y":0},"i":{"x":0.58,"y":1},"s":[100,100],"t":0},{"o":{"x":0.65,"y":0},"i":{"x":0.35,"y":0},"s":[100,100],"t":18},{"o":{"x":0,"y":0},"i":{"x":0.58,"y":1},"s":[100,100],"t":24},{"s":[100,100],"t":30}]},"sk":{"a":0,"k":0},"p":{"a":1,"k":[{"o":{"x":0,"y":0},"i":{"x":0.58,"y":1},"s":[395.48,545.37],"t":0},{"o":{"x":0.65,"y":0},"i":{"x":0.35,"y":0},"s":[383.56,588.57],"t":18},{"o":{"x":0,"y":0},"i":{"x":0.58,"y":1},"s":[406.94,468.37],"t":24},{"s":[395.48,545.37],"t":30}]},"r":{"a":1,"k":[{"o":{"x":0,"y":0},"i":{"x":0.58,"y":1},"s":[0],"t":0},{"o":{"x":0.65,"y":0},"i":{"x":0.35,"y":0},"s":[0],"t":18},{"o":{"x":0,"y":0},"i":{"x":0.58,"y":1},"s":[0],"t":24},{"s":[0],"t":30}]},"sa":{"a":0,"k":0},"o":{"a":1,"k":[{"o":{"x":0,"y":0},"i":{"x":0.58,"y":1},"s":[100],"t":0},{"o":{"x":0.65,"y":0},"i":{"x":0.35,"y":0},"s":[100],"t":18},{"o":{"x":0,"y":0},"i":{"x":0.58,"y":1},"s":[100],"t":24},{"s":[100],"t":30}]}},"shapes":[{"ty":"sh","bm":0,"hd":false,"nm":"","d":1,"ks":{"a":1,"k":[{"o":{"x":0,"y":0},"i":{"x":0.58,"y":1},"s":[{"c":true,"i":[[0,0],[0,0],[0,0],[0,0],[0,0]],"o":[[0,0],[0,0],[0,0],[0,0],[0,0]],"v":[[323.71,0],[0,466.93],[0,534.2],[323.71,67.27],[323.71,0]]}],"t":0},{"o":{"x":0.65,"y":0},"i":{"x":0.35,"y":0},"s":[{"c":true,"i":[[0,0],[0,0],[0,0],[0,0],[0,0]],"o":[[0,0],[0,0],[0,0],[0,0],[0,0]],"v":[[347.78,0],[0,438.4],[0,501.56],[347.78,63.16],[347.78,0]]}],"t":18},{"o":{"x":0,"y":0},"i":{"x":0.58,"y":1},"s":[{"c":true,"i":[[0,0],[0,0],[0,0],[0,0],[0,0]],"o":[[0,0],[0,0],[0,0],[0,0],[0,0]],"v":[[300.6,0],[0,517.78],[0,592.38],[300.6,74.6],[300.6,0]]}],"t":24},{"s":[{"c":true,"i":[[0,0],[0,0],[0,0],[0,0],[0,0]],"o":[[0,0],[0,0],[0,0],[0,0],[0,0]],"v":[[323.71,0],[0,466.93],[0,534.2],[323.71,67.27],[323.71,0]]}],"t":30}]}},{"ty":"fl","bm":0,"hd":false,"nm":"","c":{"a":1,"k":[{"o":{"x":0,"y":0},"i":{"x":0.58,"y":1},"s":[0.2118,0.2589,0.3098],"t":0},{"o":{"x":0.65,"y":0},"i":{"x":0.35,"y":0},"s":[0.2118,0.2589,0.3098],"t":18},{"o":{"x":0,"y":0},"i":{"x":0.58,"y":1},"s":[0.2118,0.2589,0.3098],"t":24},{"s":[0.2118,0.2589,0.3098],"t":30}]},"r":1,"o":{"a":1,"k":[{"o":{"x":0,"y":0},"i":{"x":0.58,"y":1},"s":[100],"t":0},{"o":{"x":0.65,"y":0},"i":{"x":0.35,"y":0},"s":[100],"t":18},{"o":{"x":0,"y":0},"i":{"x":0.58,"y":1},"s":[100],"t":24},{"s":[100],"t":30}]}}],"ind":19},{"ty":4,"nm":"2 / Group / Vector","sr":1,"st":0,"op":31,"ip":0,"hd":false,"ddd":0,"bm":0,"hasMask":false,"ao":0,"ks":{"a":{"a":1,"k":[{"o":{"x":0,"y":0},"i":{"x":0.58,"y":1},"s":[323.71,267.1],"t":0},{"o":{"x":0.65,"y":0},"i":{"x":0.35,"y":0},"s":[347.78,250.78],"t":18},{"o":{"x":0,"y":0},"i":{"x":0.58,"y":1},"s":[300.6,296.19],"t":24},{"s":[323.71,267.1],"t":30}]},"s":{"a":1,"k":[{"o":{"x":0,"y":0},"i":{"x":0.58,"y":1},"s":[100,100],"t":0},{"o":{"x":0.65,"y":0},"i":{"x":0.35,"y":0},"s":[100,100],"t":18},{"o":{"x":0,"y":0},"i":{"x":0.58,"y":1},"s":[100,100],"t":24},{"s":[100,100],"t":30}]},"sk":{"a":0,"k":0},"p":{"a":1,"k":[{"o":{"x":0,"y":0},"i":{"x":0.58,"y":1},"s":[557.34,545.37],"t":0},{"o":{"x":0.65,"y":0},"i":{"x":0.35,"y":0},"s":[557.45,588.57],"t":18},{"o":{"x":0,"y":0},"i":{"x":0.58,"y":1},"s":[557.24,468.37],"t":24},{"s":[557.34,545.37],"t":30}]},"r":{"a":1,"k":[{"o":{"x":0,"y":0},"i":{"x":0.58,"y":1},"s":[0],"t":0},{"o":{"x":0.65,"y":0},"i":{"x":0.35,"y":0},"s":[0],"t":18},{"o":{"x":0,"y":0},"i":{"x":0.58,"y":1},"s":[0],"t":24},{"s":[0],"t":30}]},"sa":{"a":0,"k":0},"o":{"a":1,"k":[{"o":{"x":0,"y":0},"i":{"x":0.58,"y":1},"s":[100],"t":0},{"o":{"x":0.65,"y":0},"i":{"x":0.35,"y":0},"s":[100],"t":18},{"o":{"x":0,"y":0},"i":{"x":0.58,"y":1},"s":[100],"t":24},{"s":[100],"t":30}]}},"shapes":[{"ty":"sh","bm":0,"hd":false,"nm":"","d":1,"ks":{"a":1,"k":[{"o":{"x":0,"y":0},"i":{"x":0.58,"y":1},"s":[{"c":true,"i":[[0,0],[0,0],[0,0],[0,0],[0,0],[0,0],[0,0]],"o":[[0,0],[0,0],[0,0],[0,0],[0,0],[0,0],[0,0]],"v":[[323.71,0],[0,466.93],[0,534.2],[323.71,67.27],[647.42,534.2],[647.42,466.93],[323.71,0]]}],"t":0},{"o":{"x":0.65,"y":0},"i":{"x":0.35,"y":0},"s":[{"c":true,"i":[[0,0],[0,0],[0,0],[0,0],[0,0],[0,0],[0,0]],"o":[[0,0],[0,0],[0,0],[0,0],[0,0],[0,0],[0,0]],"v":[[347.78,0],[0,438.4],[0,501.56],[347.78,63.16],[695.56,501.56],[695.56,438.4],[347.78,0]]}],"t":18},{"o":{"x":0,"y":0},"i":{"x":0.58,"y":1},"s":[{"c":true,"i":[[0,0],[0,0],[0,0],[0,0],[0,0],[0,0],[0,0]],"o":[[0,0],[0,0],[0,0],[0,0],[0,0],[0,0],[0,0]],"v":[[300.6,0],[0,517.78],[0,592.38],[300.6,74.6],[601.2,592.38],[601.2,517.78],[300.6,0]]}],"t":24},{"s":[{"c":true,"i":[[0,0],[0,0],[0,0],[0,0],[0,0],[0,0],[0,0]],"o":[[0,0],[0,0],[0,0],[0,0],[0,0],[0,0],[0,0]],"v":[[323.71,0],[0,466.93],[0,534.2],[323.71,67.27],[647.42,534.2],[647.42,466.93],[323.71,0]]}],"t":30}]}},{"ty":"fl","bm":0,"hd":false,"nm":"","c":{"a":1,"k":[{"o":{"x":0,"y":0},"i":{"x":0.58,"y":1},"s":[0.0824,0.1608,0.2157],"t":0},{"o":{"x":0.65,"y":0},"i":{"x":0.35,"y":0},"s":[0.0824,0.1608,0.2157],"t":18},{"o":{"x":0,"y":0},"i":{"x":0.58,"y":1},"s":[0.0824,0.1608,0.2157],"t":24},{"s":[0.0824,0.1608,0.2157],"t":30}]},"r":1,"o":{"a":1,"k":[{"o":{"x":0,"y":0},"i":{"x":0.58,"y":1},"s":[100],"t":0},{"o":{"x":0.65,"y":0},"i":{"x":0.35,"y":0},"s":[100],"t":18},{"o":{"x":0,"y":0},"i":{"x":0.58,"y":1},"s":[100],"t":24},{"s":[100],"t":30}]}}],"ind":20},{"ty":4,"nm":"2 / Group / Group / Vector","sr":1,"st":0,"op":31,"ip":0,"hd":false,"ddd":0,"bm":0,"hasMask":false,"ao":0,"ks":{"a":{"a":1,"k":[{"o":{"x":0,"y":0},"i":{"x":0.58,"y":1},"s":[46.28,9.26],"t":0},{"o":{"x":0.65,"y":0},"i":{"x":0.35,"y":0},"s":[49.72,8.69],"t":18},{"o":{"x":0,"y":0},"i":{"x":0.58,"y":1},"s":[42.97,10.26],"t":24},{"s":[46.28,9.26],"t":30}]},"s":{"a":1,"k":[{"o":{"x":0,"y":0},"i":{"x":0.58,"y":1},"s":[100,100],"t":0},{"o":{"x":0.65,"y":0},"i":{"x":0.35,"y":0},"s":[100,100],"t":18},{"o":{"x":0,"y":0},"i":{"x":0.58,"y":1},"s":[100,100],"t":24},{"s":[100,100],"t":30}]},"sk":{"a":0,"k":0},"p":{"a":1,"k":[{"o":{"x":0,"y":0},"i":{"x":0.58,"y":1},"s":[557.37,197.22],"t":0},{"o":{"x":0.65,"y":0},"i":{"x":0.35,"y":0},"s":[557.48,261.68],"t":18},{"o":{"x":0,"y":0},"i":{"x":0.58,"y":1},"s":[557.26,82.3],"t":24},{"s":[557.37,197.22],"t":30}]},"r":{"a":1,"k":[{"o":{"x":0,"y":0},"i":{"x":0.58,"y":1},"s":[0],"t":0},{"o":{"x":0.65,"y":0},"i":{"x":0.35,"y":0},"s":[0],"t":18},{"o":{"x":0,"y":0},"i":{"x":0.58,"y":1},"s":[0],"t":24},{"s":[0],"t":30}]},"sa":{"a":0,"k":0},"o":{"a":1,"k":[{"o":{"x":0,"y":0},"i":{"x":0.58,"y":1},"s":[100],"t":0},{"o":{"x":0.65,"y":0},"i":{"x":0.35,"y":0},"s":[100],"t":18},{"o":{"x":0,"y":0},"i":{"x":0.58,"y":1},"s":[100],"t":24},{"s":[100],"t":30}]}},"shapes":[{"ty":"sh","bm":0,"hd":false,"nm":"","d":1,"ks":{"a":1,"k":[{"o":{"x":0,"y":0},"i":{"x":0.58,"y":1},"s":[{"c":true,"i":[[0,0],[0,0],[0,0],[0,0],[0,0]],"o":[[0,0],[0,0],[0,0],[0,0],[0,0]],"v":[[0,0],[92.55,0],[92.55,18.51],[0,18.51],[0,0]]}],"t":0},{"o":{"x":0.65,"y":0},"i":{"x":0.35,"y":0},"s":[{"c":true,"i":[[0,0],[0,0],[0,0],[0,0],[0,0]],"o":[[0,0],[0,0],[0,0],[0,0],[0,0]],"v":[[0,0],[99.43,0],[99.43,17.38],[0,17.38],[0,0]]}],"t":18},{"o":{"x":0,"y":0},"i":{"x":0.58,"y":1},"s":[{"c":true,"i":[[0,0],[0,0],[0,0],[0,0],[0,0]],"o":[[0,0],[0,0],[0,0],[0,0],[0,0]],"v":[[0,0],[85.94,0],[85.94,20.53],[0,20.53],[0,0]]}],"t":24},{"s":[{"c":true,"i":[[0,0],[0,0],[0,0],[0,0],[0,0]],"o":[[0,0],[0,0],[0,0],[0,0],[0,0]],"v":[[0,0],[92.55,0],[92.55,18.51],[0,18.51],[0,0]]}],"t":30}]}},{"ty":"fl","bm":0,"hd":false,"nm":"","c":{"a":1,"k":[{"o":{"x":0,"y":0},"i":{"x":0.58,"y":1},"s":[0.1647,0.2549,0.3569],"t":0},{"o":{"x":0.65,"y":0},"i":{"x":0.35,"y":0},"s":[0.1647,0.2549,0.3569],"t":18},{"o":{"x":0,"y":0},"i":{"x":0.58,"y":1},"s":[0.1647,0.2549,0.3569],"t":24},{"s":[0.1647,0.2549,0.3569],"t":30}]},"r":1,"o":{"a":1,"k":[{"o":{"x":0,"y":0},"i":{"x":0.58,"y":1},"s":[100],"t":0},{"o":{"x":0.65,"y":0},"i":{"x":0.35,"y":0},"s":[100],"t":18},{"o":{"x":0,"y":0},"i":{"x":0.58,"y":1},"s":[100],"t":24},{"s":[100],"t":30}]}}],"ind":21},{"ty":4,"nm":"2 / Group / Group / Vector","sr":1,"st":0,"op":31,"ip":0,"hd":false,"ddd":0,"bm":0,"hasMask":false,"ao":0,"ks":{"a":{"a":1,"k":[{"o":{"x":0,"y":0},"i":{"x":0.58,"y":1},"s":[9.25,76.36],"t":0},{"o":{"x":0.65,"y":0},"i":{"x":0.35,"y":0},"s":[9.94,71.69],"t":18},{"o":{"x":0,"y":0},"i":{"x":0.58,"y":1},"s":[8.59,84.67],"t":24},{"s":[9.25,76.36],"t":30}]},"s":{"a":1,"k":[{"o":{"x":0,"y":0},"i":{"x":0.58,"y":1},"s":[100,100],"t":0},{"o":{"x":0.65,"y":0},"i":{"x":0.35,"y":0},"s":[100,100],"t":18},{"o":{"x":0,"y":0},"i":{"x":0.58,"y":1},"s":[100,100],"t":24},{"s":[100,100],"t":30}]},"sk":{"a":0,"k":0},"p":{"a":1,"k":[{"o":{"x":0,"y":0},"i":{"x":0.58,"y":1},"s":[557.35,219.36],"t":0},{"o":{"x":0.65,"y":0},"i":{"x":0.35,"y":0},"s":[557.46,282.47],"t":18},{"o":{"x":0,"y":0},"i":{"x":0.58,"y":1},"s":[557.25,106.85],"t":24},{"s":[557.35,219.36],"t":30}]},"r":{"a":1,"k":[{"o":{"x":0,"y":0},"i":{"x":0.58,"y":1},"s":[0],"t":0},{"o":{"x":0.65,"y":0},"i":{"x":0.35,"y":0},"s":[0],"t":18},{"o":{"x":0,"y":0},"i":{"x":0.58,"y":1},"s":[0],"t":24},{"s":[0],"t":30}]},"sa":{"a":0,"k":0},"o":{"a":1,"k":[{"o":{"x":0,"y":0},"i":{"x":0.58,"y":1},"s":[100],"t":0},{"o":{"x":0.65,"y":0},"i":{"x":0.35,"y":0},"s":[100],"t":18},{"o":{"x":0,"y":0},"i":{"x":0.58,"y":1},"s":[100],"t":24},{"s":[100],"t":30}]}},"shapes":[{"ty":"sh","bm":0,"hd":false,"nm":"","d":1,"ks":{"a":1,"k":[{"o":{"x":0,"y":0},"i":{"x":0.58,"y":1},"s":[{"c":true,"i":[[0,0],[0,0],[0,0],[0,0],[0,0]],"o":[[0,0],[0,0],[0,0],[0,0],[0,0]],"v":[[0,0],[18.51,0],[18.51,152.71],[0,152.71],[0,0]]}],"t":0},{"o":{"x":0.65,"y":0},"i":{"x":0.35,"y":0},"s":[{"c":true,"i":[[0,0],[0,0],[0,0],[0,0],[0,0]],"o":[[0,0],[0,0],[0,0],[0,0],[0,0]],"v":[[0,0],[19.89,0],[19.89,143.38],[0,143.38],[0,0]]}],"t":18},{"o":{"x":0,"y":0},"i":{"x":0.58,"y":1},"s":[{"c":true,"i":[[0,0],[0,0],[0,0],[0,0],[0,0]],"o":[[0,0],[0,0],[0,0],[0,0],[0,0]],"v":[[0,0],[17.19,0],[17.19,169.34],[0,169.34],[0,0]]}],"t":24},{"s":[{"c":true,"i":[[0,0],[0,0],[0,0],[0,0],[0,0]],"o":[[0,0],[0,0],[0,0],[0,0],[0,0]],"v":[[0,0],[18.51,0],[18.51,152.71],[0,152.71],[0,0]]}],"t":30}]}},{"ty":"fl","bm":0,"hd":false,"nm":"","c":{"a":1,"k":[{"o":{"x":0,"y":0},"i":{"x":0.58,"y":1},"s":[0.1647,0.2549,0.3569],"t":0},{"o":{"x":0.65,"y":0},"i":{"x":0.35,"y":0},"s":[0.1647,0.2549,0.3569],"t":18},{"o":{"x":0,"y":0},"i":{"x":0.58,"y":1},"s":[0.1647,0.2549,0.3569],"t":24},{"s":[0.1647,0.2549,0.3569],"t":30}]},"r":1,"o":{"a":1,"k":[{"o":{"x":0,"y":0},"i":{"x":0.58,"y":1},"s":[100],"t":0},{"o":{"x":0.65,"y":0},"i":{"x":0.35,"y":0},"s":[100],"t":18},{"o":{"x":0,"y":0},"i":{"x":0.58,"y":1},"s":[100],"t":24},{"s":[100],"t":30}]}}],"ind":22},{"ty":4,"nm":"2 / Group / Vector","sr":1,"st":0,"op":31,"ip":0,"hd":false,"ddd":0,"bm":0,"hasMask":false,"ao":0,"ks":{"a":{"a":1,"k":[{"o":{"x":0,"y":0},"i":{"x":0.58,"y":1},"s":[310.29,223.79],"t":0},{"o":{"x":0.65,"y":0},"i":{"x":0.35,"y":0},"s":[333.36,210.12],"t":18},{"o":{"x":0,"y":0},"i":{"x":0.58,"y":1},"s":[288.14,248.16],"t":24},{"s":[310.29,223.79],"t":30}]},"s":{"a":1,"k":[{"o":{"x":0,"y":0},"i":{"x":0.58,"y":1},"s":[100,100],"t":0},{"o":{"x":0.65,"y":0},"i":{"x":0.35,"y":0},"s":[100,100],"t":18},{"o":{"x":0,"y":0},"i":{"x":0.58,"y":1},"s":[100,100],"t":24},{"s":[100,100],"t":30}]},"sk":{"a":0,"k":0},"p":{"a":1,"k":[{"o":{"x":0,"y":0},"i":{"x":0.58,"y":1},"s":[557.34,548.7],"t":0},{"o":{"x":0.65,"y":0},"i":{"x":0.35,"y":0},"s":[557.45,591.69],"t":18},{"o":{"x":0,"y":0},"i":{"x":0.58,"y":1},"s":[557.24,472.06],"t":24},{"s":[557.34,548.7],"t":30}]},"r":{"a":1,"k":[{"o":{"x":0,"y":0},"i":{"x":0.58,"y":1},"s":[0],"t":0},{"o":{"x":0.65,"y":0},"i":{"x":0.35,"y":0},"s":[0],"t":18},{"o":{"x":0,"y":0},"i":{"x":0.58,"y":1},"s":[0],"t":24},{"s":[0],"t":30}]},"sa":{"a":0,"k":0},"o":{"a":1,"k":[{"o":{"x":0,"y":0},"i":{"x":0.58,"y":1},"s":[100],"t":0},{"o":{"x":0.65,"y":0},"i":{"x":0.35,"y":0},"s":[100],"t":18},{"o":{"x":0,"y":0},"i":{"x":0.58,"y":1},"s":[100],"t":24},{"s":[100],"t":30}]}},"shapes":[{"ty":"sh","bm":0,"hd":false,"nm":"","d":1,"ks":{"a":1,"k":[{"o":{"x":0,"y":0},"i":{"x":0.58,"y":1},"s":[{"c":true,"i":[[0,0],[0,0],[0,0],[0,0],[0,0],[0,0],[0,0]],"o":[[0,0],[0,0],[0,0],[0,0],[0,0],[0,0],[0,0]],"v":[[620.58,447.58],[586.93,447.58],[310.29,48.53],[33.65,447.58],[0,447.58],[310.29,0],[620.58,447.58]]}],"t":0},{"o":{"x":0.65,"y":0},"i":{"x":0.35,"y":0},"s":[{"c":true,"i":[[0,0],[0,0],[0,0],[0,0],[0,0],[0,0],[0,0]],"o":[[0,0],[0,0],[0,0],[0,0],[0,0],[0,0],[0,0]],"v":[[666.72,420.24],[630.57,420.24],[333.36,45.57],[36.15,420.24],[0,420.24],[333.36,0],[666.72,420.24]]}],"t":18},{"o":{"x":0,"y":0},"i":{"x":0.58,"y":1},"s":[{"c":true,"i":[[0,0],[0,0],[0,0],[0,0],[0,0],[0,0],[0,0]],"o":[[0,0],[0,0],[0,0],[0,0],[0,0],[0,0],[0,0]],"v":[[576.27,496.32],[545.03,496.32],[288.14,53.82],[31.25,496.32],[0,496.32],[288.14,0],[576.27,496.32]]}],"t":24},{"s":[{"c":true,"i":[[0,0],[0,0],[0,0],[0,0],[0,0],[0,0],[0,0]],"o":[[0,0],[0,0],[0,0],[0,0],[0,0],[0,0],[0,0]],"v":[[620.58,447.58],[586.93,447.58],[310.29,48.53],[33.65,447.58],[0,447.58],[310.29,0],[620.58,447.58]]}],"t":30}]}},{"ty":"fl","bm":0,"hd":false,"nm":"","c":{"a":1,"k":[{"o":{"x":0,"y":0},"i":{"x":0.58,"y":1},"s":[0.5844,0.6079,0.6824],"t":0},{"o":{"x":0.65,"y":0},"i":{"x":0.35,"y":0},"s":[0.5844,0.6079,0.6824],"t":18},{"o":{"x":0,"y":0},"i":{"x":0.58,"y":1},"s":[0.5844,0.6079,0.6824],"t":24},{"s":[0.5844,0.6079,0.6824],"t":30}]},"r":1,"o":{"a":1,"k":[{"o":{"x":0,"y":0},"i":{"x":0.58,"y":1},"s":[100],"t":0},{"o":{"x":0.65,"y":0},"i":{"x":0.35,"y":0},"s":[100],"t":18},{"o":{"x":0,"y":0},"i":{"x":0.58,"y":1},"s":[100],"t":24},{"s":[100],"t":30}]}}],"ind":23},{"ty":4,"nm":"2 / Group / Vector","sr":1,"st":0,"op":31,"ip":0,"hd":false,"ddd":0,"bm":0,"hasMask":false,"ao":0,"ks":{"a":{"a":1,"k":[{"o":{"x":0,"y":0},"i":{"x":0.58,"y":1},"s":[65.64,65.64],"t":0},{"o":{"x":0.65,"y":0},"i":{"x":0.35,"y":0},"s":[70.52,61.63],"t":18},{"o":{"x":0,"y":0},"i":{"x":0.58,"y":1},"s":[60.95,72.79],"t":24},{"s":[65.64,65.64],"t":30}]},"s":{"a":1,"k":[{"o":{"x":0,"y":0},"i":{"x":0.58,"y":1},"s":[100,100],"t":0},{"o":{"x":0.65,"y":0},"i":{"x":0.35,"y":0},"s":[100,100],"t":18},{"o":{"x":0,"y":0},"i":{"x":0.58,"y":1},"s":[100,100],"t":24},{"s":[100,100],"t":30}]},"sk":{"a":0,"k":0},"p":{"a":1,"k":[{"o":{"x":0,"y":0},"i":{"x":0.58,"y":1},"s":[557.34,628.7],"t":0},{"o":{"x":0.65,"y":0},"i":{"x":0.35,"y":0},"s":[557.45,666.81],"t":18},{"o":{"x":0,"y":0},"i":{"x":0.58,"y":1},"s":[557.24,560.77],"t":24},{"s":[557.34,628.7],"t":30}]},"r":{"a":1,"k":[{"o":{"x":0,"y":0},"i":{"x":0.58,"y":1},"s":[0],"t":0},{"o":{"x":0.65,"y":0},"i":{"x":0.35,"y":0},"s":[0],"t":18},{"o":{"x":0,"y":0},"i":{"x":0.58,"y":1},"s":[0],"t":24},{"s":[0],"t":30}]},"sa":{"a":0,"k":0},"o":{"a":1,"k":[{"o":{"x":0,"y":0},"i":{"x":0.58,"y":1},"s":[100],"t":0},{"o":{"x":0.65,"y":0},"i":{"x":0.35,"y":0},"s":[100],"t":18},{"o":{"x":0,"y":0},"i":{"x":0.58,"y":1},"s":[100],"t":24},{"s":[100],"t":30}]}},"shapes":[{"ty":"sh","bm":0,"hd":false,"nm":"","d":1,"ks":{"a":1,"k":[{"o":{"x":0,"y":0},"i":{"x":0.58,"y":1},"s":[{"c":true,"i":[[0,0],[0,36.19],[-36.19,0],[0,-36.19],[36.19,0]],"o":[[-36.19,0],[0,-36.19],[36.19,0],[0,36.19],[0,0]],"v":[[65.64,131.28],[0,65.64],[65.64,0],[131.28,65.64],[65.64,131.28]]}],"t":0},{"o":{"x":0.65,"y":0},"i":{"x":0.35,"y":0},"s":[{"c":true,"i":[[0,0],[0,33.98],[-38.88,0],[0,-33.98],[38.88,0]],"o":[[-38.88,0],[0,-33.98],[38.88,0],[0,33.98],[0,0]],"v":[[70.52,123.26],[0,61.63],[70.52,0],[141.04,61.63],[70.52,123.26]]}],"t":18},{"o":{"x":0,"y":0},"i":{"x":0.58,"y":1},"s":[{"c":true,"i":[[0,0],[0,40.13],[-33.61,0],[0,-40.13],[33.61,0]],"o":[[-33.61,0],[0,-40.13],[33.61,0],[0,40.13],[0,0]],"v":[[60.95,145.58],[0,72.79],[60.95,0],[121.91,72.79],[60.95,145.58]]}],"t":24},{"s":[{"c":true,"i":[[0,0],[0,36.19],[-36.19,0],[0,-36.19],[36.19,0]],"o":[[-36.19,0],[0,-36.19],[36.19,0],[0,36.19],[0,0]],"v":[[65.64,131.28],[0,65.64],[65.64,0],[131.28,65.64],[65.64,131.28]]}],"t":30}]}},{"ty":"sh","bm":0,"hd":false,"nm":"","d":1,"ks":{"a":1,"k":[{"o":{"x":0,"y":0},"i":{"x":0.58,"y":1},"s":[{"c":true,"i":[[0,0],[0,-28.69],[-28.69,0],[0,28.69],[28.69,0]],"o":[[-28.69,0],[0,28.69],[28.69,0],[0,-28.69],[0,0]],"v":[[65.64,13.61],[13.61,65.64],[65.64,117.67],[117.67,65.64],[65.64,13.61]]}],"t":0},{"o":{"x":0.65,"y":0},"i":{"x":0.35,"y":0},"s":[{"c":true,"i":[[0,0],[0,-26.94],[-30.82,0],[0,26.94],[30.82,0]],"o":[[-30.82,0],[0,26.94],[30.82,0],[0,-26.94],[0,0]],"v":[[70.52,12.78],[14.62,61.63],[70.52,110.48],[126.42,61.63],[70.52,12.78]]}],"t":18},{"o":{"x":0,"y":0},"i":{"x":0.58,"y":1},"s":[{"c":true,"i":[[0,0],[0,-31.81],[-26.64,0],[0,31.81],[26.64,0]],"o":[[-26.64,0],[0,31.81],[26.64,0],[0,-31.81],[0,0]],"v":[[60.95,15.09],[12.64,72.79],[60.95,130.48],[109.27,72.79],[60.95,15.09]]}],"t":24},{"s":[{"c":true,"i":[[0,0],[0,-28.69],[-28.69,0],[0,28.69],[28.69,0]],"o":[[-28.69,0],[0,28.69],[28.69,0],[0,-28.69],[0,0]],"v":[[65.64,13.61],[13.61,65.64],[65.64,117.67],[117.67,65.64],[65.64,13.61]]}],"t":30}]}},{"ty":"fl","bm":0,"hd":false,"nm":"","c":{"a":1,"k":[{"o":{"x":0,"y":0},"i":{"x":0.58,"y":1},"s":[0.5844,0.6157,0.6902],"t":0},{"o":{"x":0.65,"y":0},"i":{"x":0.35,"y":0},"s":[0.5844,0.6157,0.6902],"t":18},{"o":{"x":0,"y":0},"i":{"x":0.58,"y":1},"s":[0.5844,0.6157,0.6902],"t":24},{"s":[0.5844,0.6157,0.6902],"t":30}]},"r":1,"o":{"a":1,"k":[{"o":{"x":0,"y":0},"i":{"x":0.58,"y":1},"s":[100],"t":0},{"o":{"x":0.65,"y":0},"i":{"x":0.35,"y":0},"s":[100],"t":18},{"o":{"x":0,"y":0},"i":{"x":0.58,"y":1},"s":[100],"t":24},{"s":[100],"t":30}]}}],"ind":24},{"ty":4,"nm":"2 / Group / Vector","sr":1,"st":0,"op":31,"ip":0,"hd":false,"ddd":0,"bm":0,"hasMask":false,"ao":0,"ks":{"a":{"a":1,"k":[{"o":{"x":0,"y":0},"i":{"x":0.58,"y":1},"s":[46.92,46.92],"t":0},{"o":{"x":0.65,"y":0},"i":{"x":0.35,"y":0},"s":[50.41,44.05],"t":18},{"o":{"x":0,"y":0},"i":{"x":0.58,"y":1},"s":[43.57,52.03],"t":24},{"s":[46.92,46.92],"t":30}]},"s":{"a":1,"k":[{"o":{"x":0,"y":0},"i":{"x":0.58,"y":1},"s":[100,100],"t":0},{"o":{"x":0.65,"y":0},"i":{"x":0.35,"y":0},"s":[100,100],"t":18},{"o":{"x":0,"y":0},"i":{"x":0.58,"y":1},"s":[100,100],"t":24},{"s":[100,100],"t":30}]},"sk":{"a":0,"k":0},"p":{"a":1,"k":[{"o":{"x":0,"y":0},"i":{"x":0.58,"y":1},"s":[557.51,635.9],"t":0},{"o":{"x":0.65,"y":0},"i":{"x":0.35,"y":0},"s":[557.63,673.57],"t":18},{"o":{"x":0,"y":0},"i":{"x":0.58,"y":1},"s":[557.39,568.76],"t":24},{"s":[557.51,635.9],"t":30}]},"r":{"a":1,"k":[{"o":{"x":0,"y":0},"i":{"x":0.58,"y":1},"s":[0],"t":0},{"o":{"x":0.65,"y":0},"i":{"x":0.35,"y":0},"s":[0],"t":18},{"o":{"x":0,"y":0},"i":{"x":0.58,"y":1},"s":[0],"t":24},{"s":[0],"t":30}]},"sa":{"a":0,"k":0},"o":{"a":1,"k":[{"o":{"x":0,"y":0},"i":{"x":0.58,"y":1},"s":[100],"t":0},{"o":{"x":0.65,"y":0},"i":{"x":0.35,"y":0},"s":[100],"t":18},{"o":{"x":0,"y":0},"i":{"x":0.58,"y":1},"s":[100],"t":24},{"s":[100],"t":30}]}},"shapes":[{"ty":"sh","bm":0,"hd":false,"nm":"","d":1,"ks":{"a":1,"k":[{"o":{"x":0,"y":0},"i":{"x":0.58,"y":1},"s":[{"c":true,"i":[[0,0],[25.91,0],[0,25.91],[-25.91,0],[0,-25.91]],"o":[[0,25.91],[-25.91,0],[0,-25.91],[25.91,0],[0,0]],"v":[[93.84,46.92],[46.92,93.84],[0,46.92],[46.92,0],[93.84,46.92]]}],"t":0},{"o":{"x":0.65,"y":0},"i":{"x":0.35,"y":0},"s":[{"c":true,"i":[[0,0],[27.84,0],[0,24.33],[-27.84,0],[0,-24.33]],"o":[[0,24.33],[-27.84,0],[0,-24.33],[27.84,0],[0,0]],"v":[[100.82,44.05],[50.41,88.11],[0,44.05],[50.41,0],[100.82,44.05]]}],"t":18},{"o":{"x":0,"y":0},"i":{"x":0.58,"y":1},"s":[{"c":true,"i":[[0,0],[24.06,0],[0,28.74],[-24.06,0],[0,-28.74]],"o":[[0,28.74],[-24.06,0],[0,-28.74],[24.06,0],[0,0]],"v":[[87.14,52.03],[43.57,104.06],[0,52.03],[43.57,0],[87.14,52.03]]}],"t":24},{"s":[{"c":true,"i":[[0,0],[25.91,0],[0,25.91],[-25.91,0],[0,-25.91]],"o":[[0,25.91],[-25.91,0],[0,-25.91],[25.91,0],[0,0]],"v":[[93.84,46.92],[46.92,93.84],[0,46.92],[46.92,0],[93.84,46.92]]}],"t":30}]}},{"ty":"fl","bm":0,"hd":false,"nm":"","c":{"a":1,"k":[{"o":{"x":0,"y":0},"i":{"x":0.58,"y":1},"s":[0.1647,0.2549,0.3569],"t":0},{"o":{"x":0.65,"y":0},"i":{"x":0.35,"y":0},"s":[0.1647,0.2549,0.3569],"t":18},{"o":{"x":0,"y":0},"i":{"x":0.58,"y":1},"s":[0.1647,0.2549,0.3569],"t":24},{"s":[0.1647,0.2549,0.3569],"t":30}]},"r":1,"o":{"a":1,"k":[{"o":{"x":0,"y":0},"i":{"x":0.58,"y":1},"s":[100],"t":0},{"o":{"x":0.65,"y":0},"i":{"x":0.35,"y":0},"s":[100],"t":18},{"o":{"x":0,"y":0},"i":{"x":0.58,"y":1},"s":[100],"t":24},{"s":[100],"t":30}]}}],"ind":25},{"ty":4,"nm":"2 / Group / Vector","sr":1,"st":0,"op":31,"ip":0,"hd":false,"ddd":0,"bm":0,"hasMask":false,"ao":0,"ks":{"a":{"a":1,"k":[{"o":{"x":0,"y":0},"i":{"x":0.58,"y":1},"s":[52.03,52.03],"t":0},{"o":{"x":0.65,"y":0},"i":{"x":0.35,"y":0},"s":[52.49,52.49],"t":18},{"o":{"x":0,"y":0},"i":{"x":0.58,"y":1},"s":[53.21,53.21],"t":24},{"s":[52.03,52.03],"t":30}]},"s":{"a":1,"k":[{"o":{"x":0,"y":0},"i":{"x":0.58,"y":1},"s":[100,100],"t":0},{"o":{"x":0.65,"y":0},"i":{"x":0.35,"y":0},"s":[106.49,93.06],"t":18},{"o":{"x":0,"y":0},"i":{"x":0.58,"y":1},"s":[90.8,108.43],"t":24},{"s":[100,100],"t":30}]},"sk":{"a":0,"k":0},"p":{"a":1,"k":[{"o":{"x":0,"y":0},"i":{"x":0.58,"y":1},"s":[557.34,628.69],"t":0},{"o":{"x":0.65,"y":0},"i":{"x":0.35,"y":0},"s":[552.46,671.78],"t":18},{"o":{"x":0,"y":0},"i":{"x":0.58,"y":1},"s":[563.87,554.13],"t":24},{"s":[557.34,628.69],"t":30}]},"r":{"a":1,"k":[{"o":{"x":0,"y":0},"i":{"x":0.58,"y":1},"s":[-45],"t":0},{"o":{"x":0.65,"y":0},"i":{"x":0.35,"y":0},"s":[-41.15],"t":18},{"o":{"x":0,"y":0},"i":{"x":0.58,"y":1},"s":[-50.06],"t":24},{"s":[-45],"t":30}]},"sa":{"a":0,"k":0},"o":{"a":1,"k":[{"o":{"x":0,"y":0},"i":{"x":0.58,"y":1},"s":[100],"t":0},{"o":{"x":0.65,"y":0},"i":{"x":0.35,"y":0},"s":[100],"t":18},{"o":{"x":0,"y":0},"i":{"x":0.58,"y":1},"s":[100],"t":24},{"s":[100],"t":30}]}},"shapes":[{"ty":"sh","bm":0,"hd":false,"nm":"","d":1,"ks":{"a":1,"k":[{"o":{"x":0,"y":0},"i":{"x":0.58,"y":1},"s":[{"c":true,"i":[[0,0],[28.74,0],[0,28.74],[-28.74,0],[0,-28.74]],"o":[[0,28.74],[-28.74,0],[0,-28.74],[28.74,0],[0,0]],"v":[[104.06,52.03],[52.03,104.06],[0,52.03],[52.03,0],[104.06,52.03]]}],"t":0},{"o":{"x":0.65,"y":0},"i":{"x":0.35,"y":0},"s":[{"c":true,"i":[[0,0],[28.99,0],[0,28.99],[-28.99,0],[0,-28.99]],"o":[[0,28.99],[-28.99,0],[0,-28.99],[28.99,0],[0,0]],"v":[[104.99,52.49],[52.49,104.99],[0,52.49],[52.49,0],[104.99,52.49]]}],"t":18},{"o":{"x":0,"y":0},"i":{"x":0.58,"y":1},"s":[{"c":true,"i":[[0,0],[29.39,0],[0,29.39],[-29.39,0],[0,-29.39]],"o":[[0,29.39],[-29.39,0],[0,-29.39],[29.39,0],[0,0]],"v":[[106.43,53.21],[53.21,106.43],[0,53.21],[53.21,0],[106.43,53.21]]}],"t":24},{"s":[{"c":true,"i":[[0,0],[28.74,0],[0,28.74],[-28.74,0],[0,-28.74]],"o":[[0,28.74],[-28.74,0],[0,-28.74],[28.74,0],[0,0]],"v":[[104.06,52.03],[52.03,104.06],[0,52.03],[52.03,0],[104.06,52.03]]}],"t":30}]}},{"ty":"fl","bm":0,"hd":false,"nm":"","c":{"a":1,"k":[{"o":{"x":0,"y":0},"i":{"x":0.58,"y":1},"s":[0.0824,0.1608,0.2157],"t":0},{"o":{"x":0.65,"y":0},"i":{"x":0.35,"y":0},"s":[0.0824,0.1608,0.2157],"t":18},{"o":{"x":0,"y":0},"i":{"x":0.58,"y":1},"s":[0.0824,0.1608,0.2157],"t":24},{"s":[0.0824,0.1608,0.2157],"t":30}]},"r":1,"o":{"a":1,"k":[{"o":{"x":0,"y":0},"i":{"x":0.58,"y":1},"s":[100],"t":0},{"o":{"x":0.65,"y":0},"i":{"x":0.35,"y":0},"s":[100],"t":18},{"o":{"x":0,"y":0},"i":{"x":0.58,"y":1},"s":[100],"t":24},{"s":[100],"t":30}]}}],"ind":26},{"ty":4,"nm":"2 / Group / Vector","sr":1,"st":0,"op":31,"ip":0,"hd":false,"ddd":0,"bm":0,"hasMask":false,"ao":0,"ks":{"a":{"a":1,"k":[{"o":{"x":0,"y":0},"i":{"x":0.58,"y":1},"s":[101.58,164.71],"t":0},{"o":{"x":0.65,"y":0},"i":{"x":0.35,"y":0},"s":[109.13,154.65],"t":18},{"o":{"x":0,"y":0},"i":{"x":0.58,"y":1},"s":[94.33,182.65],"t":24},{"s":[101.58,164.71],"t":30}]},"s":{"a":1,"k":[{"o":{"x":0,"y":0},"i":{"x":0.58,"y":1},"s":[100,100],"t":0},{"o":{"x":0.65,"y":0},"i":{"x":0.35,"y":0},"s":[100,100],"t":18},{"o":{"x":0,"y":0},"i":{"x":0.58,"y":1},"s":[100,100],"t":24},{"s":[100,100],"t":30}]},"sk":{"a":0,"k":0},"p":{"a":1,"k":[{"o":{"x":0,"y":0},"i":{"x":0.58,"y":1},"s":[557.34,1042.42],"t":0},{"o":{"x":0.65,"y":0},"i":{"x":0.35,"y":0},"s":[557.45,1055.25],"t":18},{"o":{"x":0,"y":0},"i":{"x":0.58,"y":1},"s":[557.24,1019.54],"t":24},{"s":[557.34,1042.42],"t":30}]},"r":{"a":1,"k":[{"o":{"x":0,"y":0},"i":{"x":0.58,"y":1},"s":[0],"t":0},{"o":{"x":0.65,"y":0},"i":{"x":0.35,"y":0},"s":[0],"t":18},{"o":{"x":0,"y":0},"i":{"x":0.58,"y":1},"s":[0],"t":24},{"s":[0],"t":30}]},"sa":{"a":0,"k":0},"o":{"a":1,"k":[{"o":{"x":0,"y":0},"i":{"x":0.58,"y":1},"s":[100],"t":0},{"o":{"x":0.65,"y":0},"i":{"x":0.35,"y":0},"s":[100],"t":18},{"o":{"x":0,"y":0},"i":{"x":0.58,"y":1},"s":[100],"t":24},{"s":[100],"t":30}]}},"shapes":[{"ty":"sh","bm":0,"hd":false,"nm":"","d":1,"ks":{"a":1,"k":[{"o":{"x":0,"y":0},"i":{"x":0.58,"y":1},"s":[{"c":true,"i":[[0,0],[0,0],[0,0],[0,0],[0,0],[0,0],[0,0],[0,0],[0,0]],"o":[[0,0],[0,0],[0,0],[0,0],[0,0],[0,0],[0,0],[0,0],[0,0]],"v":[[203.16,329.43],[183.33,329.43],[183.33,19.83],[19.83,19.83],[19.83,329.43],[0,329.43],[0,0],[203.16,0],[203.16,329.43]]}],"t":0},{"o":{"x":0.65,"y":0},"i":{"x":0.35,"y":0},"s":[{"c":true,"i":[[0,0],[0,0],[0,0],[0,0],[0,0],[0,0],[0,0],[0,0],[0,0]],"o":[[0,0],[0,0],[0,0],[0,0],[0,0],[0,0],[0,0],[0,0],[0,0]],"v":[[218.26,309.3],[196.96,309.3],[196.96,18.62],[21.3,18.62],[21.3,309.3],[0,309.3],[0,0],[218.26,0],[218.26,309.3]]}],"t":18},{"o":{"x":0,"y":0},"i":{"x":0.58,"y":1},"s":[{"c":true,"i":[[0,0],[0,0],[0,0],[0,0],[0,0],[0,0],[0,0],[0,0],[0,0]],"o":[[0,0],[0,0],[0,0],[0,0],[0,0],[0,0],[0,0],[0,0],[0,0]],"v":[[188.66,365.31],[170.24,365.31],[170.24,21.99],[18.41,21.99],[18.41,365.31],[0,365.31],[0,0],[188.66,0],[188.66,365.31]]}],"t":24},{"s":[{"c":true,"i":[[0,0],[0,0],[0,0],[0,0],[0,0],[0,0],[0,0],[0,0],[0,0]],"o":[[0,0],[0,0],[0,0],[0,0],[0,0],[0,0],[0,0],[0,0],[0,0]],"v":[[203.16,329.43],[183.33,329.43],[183.33,19.83],[19.83,19.83],[19.83,329.43],[0,329.43],[0,0],[203.16,0],[203.16,329.43]]}],"t":30}]}},{"ty":"fl","bm":0,"hd":false,"nm":"","c":{"a":1,"k":[{"o":{"x":0,"y":0},"i":{"x":0.58,"y":1},"s":[0.5844,0.6157,0.6902],"t":0},{"o":{"x":0.65,"y":0},"i":{"x":0.35,"y":0},"s":[0.5844,0.6157,0.6902],"t":18},{"o":{"x":0,"y":0},"i":{"x":0.58,"y":1},"s":[0.5844,0.6157,0.6902],"t":24},{"s":[0.5844,0.6157,0.6902],"t":30}]},"r":1,"o":{"a":1,"k":[{"o":{"x":0,"y":0},"i":{"x":0.58,"y":1},"s":[100],"t":0},{"o":{"x":0.65,"y":0},"i":{"x":0.35,"y":0},"s":[100],"t":18},{"o":{"x":0,"y":0},"i":{"x":0.58,"y":1},"s":[100],"t":24},{"s":[100],"t":30}]}}],"ind":27},{"ty":4,"nm":"2 / Group / Vector","sr":1,"st":0,"op":31,"ip":0,"hd":false,"ddd":0,"bm":0,"hasMask":false,"ao":0,"ks":{"a":{"a":1,"k":[{"o":{"x":0,"y":0},"i":{"x":0.58,"y":1},"s":[21.77,66],"t":0},{"o":{"x":0.65,"y":0},"i":{"x":0.35,"y":0},"s":[23.39,61.97],"t":18},{"o":{"x":0,"y":0},"i":{"x":0.58,"y":1},"s":[20.22,73.19],"t":24},{"s":[21.77,66],"t":30}]},"s":{"a":1,"k":[{"o":{"x":0,"y":0},"i":{"x":0.58,"y":1},"s":[100,100],"t":0},{"o":{"x":0.65,"y":0},"i":{"x":0.35,"y":0},"s":[100,100],"t":18},{"o":{"x":0,"y":0},"i":{"x":0.58,"y":1},"s":[100,100],"t":24},{"s":[100,100],"t":30}]},"sk":{"a":0,"k":0},"p":{"a":1,"k":[{"o":{"x":0,"y":0},"i":{"x":0.58,"y":1},"s":[617.32,1141.13],"t":0},{"o":{"x":0.65,"y":0},"i":{"x":0.35,"y":0},"s":[621.89,1147.93],"t":18},{"o":{"x":0,"y":0},"i":{"x":0.58,"y":1},"s":[612.93,1129.01],"t":24},{"s":[617.32,1141.13],"t":30}]},"r":{"a":1,"k":[{"o":{"x":0,"y":0},"i":{"x":0.58,"y":1},"s":[0],"t":0},{"o":{"x":0.65,"y":0},"i":{"x":0.35,"y":0},"s":[0],"t":18},{"o":{"x":0,"y":0},"i":{"x":0.58,"y":1},"s":[0],"t":24},{"s":[0],"t":30}]},"sa":{"a":0,"k":0},"o":{"a":1,"k":[{"o":{"x":0,"y":0},"i":{"x":0.58,"y":1},"s":[100],"t":0},{"o":{"x":0.65,"y":0},"i":{"x":0.35,"y":0},"s":[100],"t":18},{"o":{"x":0,"y":0},"i":{"x":0.58,"y":1},"s":[100],"t":24},{"s":[100],"t":30}]}},"shapes":[{"ty":"sh","bm":0,"hd":false,"nm":"","d":1,"ks":{"a":1,"k":[{"o":{"x":0,"y":0},"i":{"x":0.58,"y":1},"s":[{"c":true,"i":[[0,0],[0,0],[0,0],[0,0],[0,0],[-9.77,0],[0,0]],"o":[[0,0],[0,0],[0,0],[0,0],[0,-9.78],[0,0],[0,0]],"v":[[17.72,0],[43.54,0],[43.54,132],[0,132],[0,17.72],[17.71,0.01],[17.72,0]]}],"t":0},{"o":{"x":0.65,"y":0},"i":{"x":0.35,"y":0},"s":[{"c":true,"i":[[0,0],[0,0],[0,0],[0,0],[0,0],[-10.5,0],[0,0]],"o":[[0,0],[0,0],[0,0],[0,0],[0,-9.18],[0,0],[0,0]],"v":[[19.04,0],[46.78,0],[46.78,123.94],[0,123.94],[0,16.64],[19.03,0.01],[19.04,0]]}],"t":18},{"o":{"x":0,"y":0},"i":{"x":0.58,"y":1},"s":[{"c":true,"i":[[0,0],[0,0],[0,0],[0,0],[0,0],[-9.07,0],[0,0]],"o":[[0,0],[0,0],[0,0],[0,0],[0,-10.85],[0,0],[0,0]],"v":[[16.45,0],[40.43,0],[40.43,146.38],[0,146.38],[0,19.65],[16.45,0.01],[16.45,0]]}],"t":24},{"s":[{"c":true,"i":[[0,0],[0,0],[0,0],[0,0],[0,0],[-9.77,0],[0,0]],"o":[[0,0],[0,0],[0,0],[0,0],[0,-9.78],[0,0],[0,0]],"v":[[17.72,0],[43.54,0],[43.54,132],[0,132],[0,17.72],[17.71,0.01],[17.72,0]]}],"t":30}]}},{"ty":"fl","bm":0,"hd":false,"nm":"","c":{"a":1,"k":[{"o":{"x":0,"y":0},"i":{"x":0.58,"y":1},"s":[0.0824,0.1608,0.2157],"t":0},{"o":{"x":0.65,"y":0},"i":{"x":0.35,"y":0},"s":[0.0824,0.1608,0.2157],"t":18},{"o":{"x":0,"y":0},"i":{"x":0.58,"y":1},"s":[0.0824,0.1608,0.2157],"t":24},{"s":[0.0824,0.1608,0.2157],"t":30}]},"r":1,"o":{"a":1,"k":[{"o":{"x":0,"y":0},"i":{"x":0.58,"y":1},"s":[100],"t":0},{"o":{"x":0.65,"y":0},"i":{"x":0.35,"y":0},"s":[100],"t":18},{"o":{"x":0,"y":0},"i":{"x":0.58,"y":1},"s":[100],"t":24},{"s":[100],"t":30}]}}],"ind":28},{"ty":4,"nm":"2 / Group / Vector","sr":1,"st":0,"op":31,"ip":0,"hd":false,"ddd":0,"bm":0,"hasMask":false,"ao":0,"ks":{"a":{"a":1,"k":[{"o":{"x":0,"y":0},"i":{"x":0.58,"y":1},"s":[21.77,66],"t":0},{"o":{"x":0.65,"y":0},"i":{"x":0.35,"y":0},"s":[23.39,61.97],"t":18},{"o":{"x":0,"y":0},"i":{"x":0.58,"y":1},"s":[20.22,73.19],"t":24},{"s":[21.77,66],"t":30}]},"s":{"a":1,"k":[{"o":{"x":0,"y":0},"i":{"x":0.58,"y":1},"s":[100,100],"t":0},{"o":{"x":0.65,"y":0},"i":{"x":0.35,"y":0},"s":[100,100],"t":18},{"o":{"x":0,"y":0},"i":{"x":0.58,"y":1},"s":[100,100],"t":24},{"s":[100,100],"t":30}]},"sk":{"a":0,"k":0},"p":{"a":1,"k":[{"o":{"x":0,"y":0},"i":{"x":0.58,"y":1},"s":[497.35,1141.12],"t":0},{"o":{"x":0.65,"y":0},"i":{"x":0.35,"y":0},"s":[493,1147.92],"t":18},{"o":{"x":0,"y":0},"i":{"x":0.58,"y":1},"s":[501.53,1129],"t":24},{"s":[497.35,1141.12],"t":30}]},"r":{"a":1,"k":[{"o":{"x":0,"y":0},"i":{"x":0.58,"y":1},"s":[0],"t":0},{"o":{"x":0.65,"y":0},"i":{"x":0.35,"y":0},"s":[0],"t":18},{"o":{"x":0,"y":0},"i":{"x":0.58,"y":1},"s":[0],"t":24},{"s":[0],"t":30}]},"sa":{"a":0,"k":0},"o":{"a":1,"k":[{"o":{"x":0,"y":0},"i":{"x":0.58,"y":1},"s":[100],"t":0},{"o":{"x":0.65,"y":0},"i":{"x":0.35,"y":0},"s":[100],"t":18},{"o":{"x":0,"y":0},"i":{"x":0.58,"y":1},"s":[100],"t":24},{"s":[100],"t":30}]}},"shapes":[{"ty":"sh","bm":0,"hd":false,"nm":"","d":1,"ks":{"a":1,"k":[{"o":{"x":0,"y":0},"i":{"x":0.58,"y":1},"s":[{"c":true,"i":[[0,0],[0,0],[0,-9.77],[0,0],[0,0],[0,0],[0,0],[0,0]],"o":[[0,0],[9.78,0],[0,0],[0,0],[0,0],[0,0],[0,0],[0,0]],"v":[[0.01,0.01],[25.83,0.01],[43.54,17.72],[43.54,132],[0,132],[0,0],[0.01,0],[0.01,0.01]]}],"t":0},{"o":{"x":0.65,"y":0},"i":{"x":0.35,"y":0},"s":[{"c":true,"i":[[0,0],[0,0],[0,-9.17],[0,0],[0,0],[0,0],[0,0],[0,0]],"o":[[0,0],[10.51,0],[0,0],[0,0],[0,0],[0,0],[0,0],[0,0]],"v":[[0.01,0.01],[27.75,0.01],[46.78,16.64],[46.78,123.94],[0,123.94],[0,0],[0.01,0],[0.01,0.01]]}],"t":18},{"o":{"x":0,"y":0},"i":{"x":0.58,"y":1},"s":[{"c":true,"i":[[0,0],[0,0],[0,-10.83],[0,0],[0,0],[0,0],[0,0],[0,0]],"o":[[0,0],[9.08,0],[0,0],[0,0],[0,0],[0,0],[0,0],[0,0]],"v":[[0.01,0.01],[23.99,0.01],[40.43,19.65],[40.43,146.38],[0,146.38],[0,0],[0.01,0],[0.01,0.01]]}],"t":24},{"s":[{"c":true,"i":[[0,0],[0,0],[0,-9.77],[0,0],[0,0],[0,0],[0,0],[0,0]],"o":[[0,0],[9.78,0],[0,0],[0,0],[0,0],[0,0],[0,0],[0,0]],"v":[[0.01,0.01],[25.83,0.01],[43.54,17.72],[43.54,132],[0,132],[0,0],[0.01,0],[0.01,0.01]]}],"t":30}]}},{"ty":"fl","bm":0,"hd":false,"nm":"","c":{"a":1,"k":[{"o":{"x":0,"y":0},"i":{"x":0.58,"y":1},"s":[0.0824,0.1608,0.2157],"t":0},{"o":{"x":0.65,"y":0},"i":{"x":0.35,"y":0},"s":[0.0824,0.1608,0.2157],"t":18},{"o":{"x":0,"y":0},"i":{"x":0.58,"y":1},"s":[0.0824,0.1608,0.2157],"t":24},{"s":[0.0824,0.1608,0.2157],"t":30}]},"r":1,"o":{"a":1,"k":[{"o":{"x":0,"y":0},"i":{"x":0.58,"y":1},"s":[100],"t":0},{"o":{"x":0.65,"y":0},"i":{"x":0.35,"y":0},"s":[100],"t":18},{"o":{"x":0,"y":0},"i":{"x":0.58,"y":1},"s":[100],"t":24},{"s":[100],"t":30}]}}],"ind":29},{"ty":4,"nm":"2 / Group / Vector","sr":1,"st":0,"op":31,"ip":0,"hd":false,"ddd":0,"bm":0,"hasMask":false,"ao":0,"ks":{"a":{"a":1,"k":[{"o":{"x":0,"y":0},"i":{"x":0.58,"y":1},"s":[81.75,12.57],"t":0},{"o":{"x":0.65,"y":0},"i":{"x":0.35,"y":0},"s":[87.83,11.81],"t":18},{"o":{"x":0,"y":0},"i":{"x":0.58,"y":1},"s":[75.91,13.94],"t":24},{"s":[81.75,12.57],"t":30}]},"s":{"a":1,"k":[{"o":{"x":0,"y":0},"i":{"x":0.58,"y":1},"s":[100,100],"t":0},{"o":{"x":0.65,"y":0},"i":{"x":0.35,"y":0},"s":[100,100],"t":18},{"o":{"x":0,"y":0},"i":{"x":0.58,"y":1},"s":[100,100],"t":24},{"s":[100,100],"t":30}]},"sk":{"a":0,"k":0},"p":{"a":1,"k":[{"o":{"x":0,"y":0},"i":{"x":0.58,"y":1},"s":[557.34,910.11],"t":0},{"o":{"x":0.65,"y":0},"i":{"x":0.35,"y":0},"s":[557.45,931.02],"t":18},{"o":{"x":0,"y":0},"i":{"x":0.58,"y":1},"s":[557.24,872.82],"t":24},{"s":[557.34,910.11],"t":30}]},"r":{"a":1,"k":[{"o":{"x":0,"y":0},"i":{"x":0.58,"y":1},"s":[0],"t":0},{"o":{"x":0.65,"y":0},"i":{"x":0.35,"y":0},"s":[0],"t":18},{"o":{"x":0,"y":0},"i":{"x":0.58,"y":1},"s":[0],"t":24},{"s":[0],"t":30}]},"sa":{"a":0,"k":0},"o":{"a":1,"k":[{"o":{"x":0,"y":0},"i":{"x":0.58,"y":1},"s":[100],"t":0},{"o":{"x":0.65,"y":0},"i":{"x":0.35,"y":0},"s":[100],"t":18},{"o":{"x":0,"y":0},"i":{"x":0.58,"y":1},"s":[100],"t":24},{"s":[100],"t":30}]}},"shapes":[{"ty":"sh","bm":0,"hd":false,"nm":"","d":1,"ks":{"a":1,"k":[{"o":{"x":0,"y":0},"i":{"x":0.58,"y":1},"s":[{"c":true,"i":[[0,0],[0,0],[0,0],[0,0],[0,0]],"o":[[0,0],[0,0],[0,0],[0,0],[0,0]],"v":[[0,0],[163.5,0],[163.5,25.15],[0,25.15],[0,0]]}],"t":0},{"o":{"x":0.65,"y":0},"i":{"x":0.35,"y":0},"s":[{"c":true,"i":[[0,0],[0,0],[0,0],[0,0],[0,0]],"o":[[0,0],[0,0],[0,0],[0,0],[0,0]],"v":[[0,0],[175.66,0],[175.66,23.61],[0,23.61],[0,0]]}],"t":18},{"o":{"x":0,"y":0},"i":{"x":0.58,"y":1},"s":[{"c":true,"i":[[0,0],[0,0],[0,0],[0,0],[0,0]],"o":[[0,0],[0,0],[0,0],[0,0],[0,0]],"v":[[0,0],[151.83,0],[151.83,27.89],[0,27.89],[0,0]]}],"t":24},{"s":[{"c":true,"i":[[0,0],[0,0],[0,0],[0,0],[0,0]],"o":[[0,0],[0,0],[0,0],[0,0],[0,0]],"v":[[0,0],[163.5,0],[163.5,25.15],[0,25.15],[0,0]]}],"t":30}]}},{"ty":"fl","bm":0,"hd":false,"nm":"","c":{"a":1,"k":[{"o":{"x":0,"y":0},"i":{"x":0.58,"y":1},"s":[0.0824,0.1608,0.2157],"t":0},{"o":{"x":0.65,"y":0},"i":{"x":0.35,"y":0},"s":[0.0824,0.1608,0.2157],"t":18},{"o":{"x":0,"y":0},"i":{"x":0.58,"y":1},"s":[0.0824,0.1608,0.2157],"t":24},{"s":[0.0824,0.1608,0.2157],"t":30}]},"r":1,"o":{"a":1,"k":[{"o":{"x":0,"y":0},"i":{"x":0.58,"y":1},"s":[100],"t":0},{"o":{"x":0.65,"y":0},"i":{"x":0.35,"y":0},"s":[100],"t":18},{"o":{"x":0,"y":0},"i":{"x":0.58,"y":1},"s":[100],"t":24},{"s":[100],"t":30}]}}],"ind":30},{"ty":4,"nm":"2 / Group / Vector","sr":1,"st":0,"op":31,"ip":0,"hd":false,"ddd":0,"bm":0,"hasMask":false,"ao":0,"ks":{"a":{"a":1,"k":[{"o":{"x":0,"y":0},"i":{"x":0.58,"y":1},"s":[81.75,154.8],"t":0},{"o":{"x":0.65,"y":0},"i":{"x":0.35,"y":0},"s":[87.83,145.34],"t":18},{"o":{"x":0,"y":0},"i":{"x":0.58,"y":1},"s":[75.91,171.66],"t":24},{"s":[81.75,154.8],"t":30}]},"s":{"a":1,"k":[{"o":{"x":0,"y":0},"i":{"x":0.58,"y":1},"s":[100,100],"t":0},{"o":{"x":0.65,"y":0},"i":{"x":0.35,"y":0},"s":[100,100],"t":18},{"o":{"x":0,"y":0},"i":{"x":0.58,"y":1},"s":[100,100],"t":24},{"s":[100,100],"t":30}]},"sk":{"a":0,"k":0},"p":{"a":1,"k":[{"o":{"x":0,"y":0},"i":{"x":0.58,"y":1},"s":[557.34,1052.33],"t":0},{"o":{"x":0.65,"y":0},"i":{"x":0.35,"y":0},"s":[557.45,1064.56],"t":18},{"o":{"x":0,"y":0},"i":{"x":0.58,"y":1},"s":[557.24,1030.54],"t":24},{"s":[557.34,1052.33],"t":30}]},"r":{"a":1,"k":[{"o":{"x":0,"y":0},"i":{"x":0.58,"y":1},"s":[0],"t":0},{"o":{"x":0.65,"y":0},"i":{"x":0.35,"y":0},"s":[0],"t":18},{"o":{"x":0,"y":0},"i":{"x":0.58,"y":1},"s":[0],"t":24},{"s":[0],"t":30}]},"sa":{"a":0,"k":0},"o":{"a":1,"k":[{"o":{"x":0,"y":0},"i":{"x":0.58,"y":1},"s":[100],"t":0},{"o":{"x":0.65,"y":0},"i":{"x":0.35,"y":0},"s":[100],"t":18},{"o":{"x":0,"y":0},"i":{"x":0.58,"y":1},"s":[100],"t":24},{"s":[100],"t":30}]}},"shapes":[{"ty":"sh","bm":0,"hd":false,"nm":"","d":1,"ks":{"a":1,"k":[{"o":{"x":0,"y":0},"i":{"x":0.58,"y":1},"s":[{"c":true,"i":[[0,0],[0,0],[0,0],[0,0],[0,0]],"o":[[0,0],[0,0],[0,0],[0,0],[0,0]],"v":[[0,0],[163.5,0],[163.5,309.6],[0,309.6],[0,0]]}],"t":0},{"o":{"x":0.65,"y":0},"i":{"x":0.35,"y":0},"s":[{"c":true,"i":[[0,0],[0,0],[0,0],[0,0],[0,0]],"o":[[0,0],[0,0],[0,0],[0,0],[0,0]],"v":[[0,0],[175.66,0],[175.66,290.69],[0,290.69],[0,0]]}],"t":18},{"o":{"x":0,"y":0},"i":{"x":0.58,"y":1},"s":[{"c":true,"i":[[0,0],[0,0],[0,0],[0,0],[0,0]],"o":[[0,0],[0,0],[0,0],[0,0],[0,0]],"v":[[0,0],[151.83,0],[151.83,343.32],[0,343.32],[0,0]]}],"t":24},{"s":[{"c":true,"i":[[0,0],[0,0],[0,0],[0,0],[0,0]],"o":[[0,0],[0,0],[0,0],[0,0],[0,0]],"v":[[0,0],[163.5,0],[163.5,309.6],[0,309.6],[0,0]]}],"t":30}]}},{"ty":"fl","bm":0,"hd":false,"nm":"","c":{"a":1,"k":[{"o":{"x":0,"y":0},"i":{"x":0.58,"y":1},"s":[0.1647,0.2549,0.3569],"t":0},{"o":{"x":0.65,"y":0},"i":{"x":0.35,"y":0},"s":[0.1647,0.2549,0.3569],"t":18},{"o":{"x":0,"y":0},"i":{"x":0.58,"y":1},"s":[0.1647,0.2549,0.3569],"t":24},{"s":[0.1647,0.2549,0.3569],"t":30}]},"r":1,"o":{"a":1,"k":[{"o":{"x":0,"y":0},"i":{"x":0.58,"y":1},"s":[100],"t":0},{"o":{"x":0.65,"y":0},"i":{"x":0.35,"y":0},"s":[100],"t":18},{"o":{"x":0,"y":0},"i":{"x":0.58,"y":1},"s":[100],"t":24},{"s":[100],"t":30}]}}],"ind":31},{"ty":4,"nm":"2 / Group / Vector","sr":1,"st":0,"op":31,"ip":0,"hd":false,"ddd":0,"bm":0,"hasMask":false,"ao":0,"ks":{"a":{"a":1,"k":[{"o":{"x":0,"y":0},"i":{"x":0.58,"y":1},"s":[257.63,9.91],"t":0},{"o":{"x":0.65,"y":0},"i":{"x":0.35,"y":0},"s":[276.78,9.31],"t":18},{"o":{"x":0,"y":0},"i":{"x":0.58,"y":1},"s":[239.23,10.99],"t":24},{"s":[257.63,9.91],"t":30}]},"s":{"a":1,"k":[{"o":{"x":0,"y":0},"i":{"x":0.58,"y":1},"s":[100,100],"t":0},{"o":{"x":0.65,"y":0},"i":{"x":0.35,"y":0},"s":[100,100],"t":18},{"o":{"x":0,"y":0},"i":{"x":0.58,"y":1},"s":[100,100],"t":24},{"s":[100,100],"t":30}]},"sk":{"a":0,"k":0},"p":{"a":1,"k":[{"o":{"x":0,"y":0},"i":{"x":0.58,"y":1},"s":[557.34,1217.04],"t":0},{"o":{"x":0.65,"y":0},"i":{"x":0.35,"y":0},"s":[557.45,1219.21],"t":18},{"o":{"x":0,"y":0},"i":{"x":0.58,"y":1},"s":[557.24,1213.19],"t":24},{"s":[557.34,1217.04],"t":30}]},"r":{"a":1,"k":[{"o":{"x":0,"y":0},"i":{"x":0.58,"y":1},"s":[0],"t":0},{"o":{"x":0.65,"y":0},"i":{"x":0.35,"y":0},"s":[0],"t":18},{"o":{"x":0,"y":0},"i":{"x":0.58,"y":1},"s":[0],"t":24},{"s":[0],"t":30}]},"sa":{"a":0,"k":0},"o":{"a":1,"k":[{"o":{"x":0,"y":0},"i":{"x":0.58,"y":1},"s":[100],"t":0},{"o":{"x":0.65,"y":0},"i":{"x":0.35,"y":0},"s":[100],"t":18},{"o":{"x":0,"y":0},"i":{"x":0.58,"y":1},"s":[100],"t":24},{"s":[100],"t":30}]}},"shapes":[{"ty":"sh","bm":0,"hd":false,"nm":"","d":1,"ks":{"a":1,"k":[{"o":{"x":0,"y":0},"i":{"x":0.58,"y":1},"s":[{"c":true,"i":[[0,0],[0,0],[0,0],[0,0],[0,0]],"o":[[0,0],[0,0],[0,0],[0,0],[0,0]],"v":[[0,0],[515.25,0],[515.25,19.83],[0,19.83],[0,0]]}],"t":0},{"o":{"x":0.65,"y":0},"i":{"x":0.35,"y":0},"s":[{"c":true,"i":[[0,0],[0,0],[0,0],[0,0],[0,0]],"o":[[0,0],[0,0],[0,0],[0,0],[0,0]],"v":[[0,0],[553.56,0],[553.56,18.62],[0,18.62],[0,0]]}],"t":18},{"o":{"x":0,"y":0},"i":{"x":0.58,"y":1},"s":[{"c":true,"i":[[0,0],[0,0],[0,0],[0,0],[0,0]],"o":[[0,0],[0,0],[0,0],[0,0],[0,0]],"v":[[0,0],[478.46,0],[478.46,21.99],[0,21.99],[0,0]]}],"t":24},{"s":[{"c":true,"i":[[0,0],[0,0],[0,0],[0,0],[0,0]],"o":[[0,0],[0,0],[0,0],[0,0],[0,0]],"v":[[0,0],[515.25,0],[515.25,19.83],[0,19.83],[0,0]]}],"t":30}]}},{"ty":"fl","bm":0,"hd":false,"nm":"","c":{"a":1,"k":[{"o":{"x":0,"y":0},"i":{"x":0.58,"y":1},"s":[0.5844,0.6157,0.6902],"t":0},{"o":{"x":0.65,"y":0},"i":{"x":0.35,"y":0},"s":[0.5844,0.6157,0.6902],"t":18},{"o":{"x":0,"y":0},"i":{"x":0.58,"y":1},"s":[0.5844,0.6157,0.6902],"t":24},{"s":[0.5844,0.6157,0.6902],"t":30}]},"r":1,"o":{"a":1,"k":[{"o":{"x":0,"y":0},"i":{"x":0.58,"y":1},"s":[100],"t":0},{"o":{"x":0.65,"y":0},"i":{"x":0.35,"y":0},"s":[100],"t":18},{"o":{"x":0,"y":0},"i":{"x":0.58,"y":1},"s":[100],"t":24},{"s":[100],"t":30}]}}],"ind":32},{"ty":4,"nm":"2 / Group / Vector","sr":1,"st":0,"op":31,"ip":0,"hd":false,"ddd":0,"bm":0,"hasMask":false,"ao":0,"ks":{"a":{"a":1,"k":[{"o":{"x":0,"y":0},"i":{"x":0.58,"y":1},"s":[257.63,12.33],"t":0},{"o":{"x":0.65,"y":0},"i":{"x":0.35,"y":0},"s":[276.78,11.57],"t":18},{"o":{"x":0,"y":0},"i":{"x":0.58,"y":1},"s":[239.23,13.67],"t":24},{"s":[257.63,12.33],"t":30}]},"s":{"a":1,"k":[{"o":{"x":0,"y":0},"i":{"x":0.58,"y":1},"s":[100,100],"t":0},{"o":{"x":0.65,"y":0},"i":{"x":0.35,"y":0},"s":[100,100],"t":18},{"o":{"x":0,"y":0},"i":{"x":0.58,"y":1},"s":[100,100],"t":24},{"s":[100,100],"t":30}]},"sk":{"a":0,"k":0},"p":{"a":1,"k":[{"o":{"x":0,"y":0},"i":{"x":0.58,"y":1},"s":[557.34,784.8],"t":0},{"o":{"x":0.65,"y":0},"i":{"x":0.35,"y":0},"s":[557.45,813.37],"t":18},{"o":{"x":0,"y":0},"i":{"x":0.58,"y":1},"s":[557.24,733.88],"t":24},{"s":[557.34,784.8],"t":30}]},"r":{"a":1,"k":[{"o":{"x":0,"y":0},"i":{"x":0.58,"y":1},"s":[0],"t":0},{"o":{"x":0.65,"y":0},"i":{"x":0.35,"y":0},"s":[0],"t":18},{"o":{"x":0,"y":0},"i":{"x":0.58,"y":1},"s":[0],"t":24},{"s":[0],"t":30}]},"sa":{"a":0,"k":0},"o":{"a":1,"k":[{"o":{"x":0,"y":0},"i":{"x":0.58,"y":1},"s":[100],"t":0},{"o":{"x":0.65,"y":0},"i":{"x":0.35,"y":0},"s":[100],"t":18},{"o":{"x":0,"y":0},"i":{"x":0.58,"y":1},"s":[100],"t":24},{"s":[100],"t":30}]}},"shapes":[{"ty":"sh","bm":0,"hd":false,"nm":"","d":1,"ks":{"a":1,"k":[{"o":{"x":0,"y":0},"i":{"x":0.58,"y":1},"s":[{"c":true,"i":[[0,0],[0,0],[0,0],[0,0],[0,0]],"o":[[0,0],[0,0],[0,0],[0,0],[0,0]],"v":[[0,0],[515.25,0],[515.25,24.65],[0,24.65],[0,0]]}],"t":0},{"o":{"x":0.65,"y":0},"i":{"x":0.35,"y":0},"s":[{"c":true,"i":[[0,0],[0,0],[0,0],[0,0],[0,0]],"o":[[0,0],[0,0],[0,0],[0,0],[0,0]],"v":[[0,0],[553.56,0],[553.56,23.14],[0,23.14],[0,0]]}],"t":18},{"o":{"x":0,"y":0},"i":{"x":0.58,"y":1},"s":[{"c":true,"i":[[0,0],[0,0],[0,0],[0,0],[0,0]],"o":[[0,0],[0,0],[0,0],[0,0],[0,0]],"v":[[0,0],[478.46,0],[478.46,27.33],[0,27.33],[0,0]]}],"t":24},{"s":[{"c":true,"i":[[0,0],[0,0],[0,0],[0,0],[0,0]],"o":[[0,0],[0,0],[0,0],[0,0],[0,0]],"v":[[0,0],[515.25,0],[515.25,24.65],[0,24.65],[0,0]]}],"t":30}]}},{"ty":"fl","bm":0,"hd":false,"nm":"","c":{"a":1,"k":[{"o":{"x":0,"y":0},"i":{"x":0.58,"y":1},"s":[0.7804,0.7804,0.851],"t":0},{"o":{"x":0.65,"y":0},"i":{"x":0.35,"y":0},"s":[0.7804,0.7804,0.851],"t":18},{"o":{"x":0,"y":0},"i":{"x":0.58,"y":1},"s":[0.7804,0.7804,0.851],"t":24},{"s":[0.7804,0.7804,0.851],"t":30}]},"r":1,"o":{"a":1,"k":[{"o":{"x":0,"y":0},"i":{"x":0.58,"y":1},"s":[100],"t":0},{"o":{"x":0.65,"y":0},"i":{"x":0.35,"y":0},"s":[100],"t":18},{"o":{"x":0,"y":0},"i":{"x":0.58,"y":1},"s":[100],"t":24},{"s":[100],"t":30}]}}],"ind":33},{"ty":4,"nm":"2 / Group / Vector","sr":1,"st":0,"op":31,"ip":0,"hd":false,"ddd":0,"bm":0,"hasMask":false,"ao":0,"ks":{"a":{"a":1,"k":[{"o":{"x":0,"y":0},"i":{"x":0.58,"y":1},"s":[257.63,217.32],"t":0},{"o":{"x":0.65,"y":0},"i":{"x":0.35,"y":0},"s":[276.78,204.04],"t":18},{"o":{"x":0,"y":0},"i":{"x":0.58,"y":1},"s":[239.23,240.99],"t":24},{"s":[257.63,217.32],"t":30}]},"s":{"a":1,"k":[{"o":{"x":0,"y":0},"i":{"x":0.58,"y":1},"s":[100,100],"t":0},{"o":{"x":0.65,"y":0},"i":{"x":0.35,"y":0},"s":[100,100],"t":18},{"o":{"x":0,"y":0},"i":{"x":0.58,"y":1},"s":[100,100],"t":24},{"s":[100,100],"t":30}]},"sk":{"a":0,"k":0},"p":{"a":1,"k":[{"o":{"x":0,"y":0},"i":{"x":0.58,"y":1},"s":[557.34,989.8],"t":0},{"o":{"x":0.65,"y":0},"i":{"x":0.35,"y":0},"s":[557.45,1005.85],"t":18},{"o":{"x":0,"y":0},"i":{"x":0.58,"y":1},"s":[557.24,961.2],"t":24},{"s":[557.34,989.8],"t":30}]},"r":{"a":1,"k":[{"o":{"x":0,"y":0},"i":{"x":0.58,"y":1},"s":[0],"t":0},{"o":{"x":0.65,"y":0},"i":{"x":0.35,"y":0},"s":[0],"t":18},{"o":{"x":0,"y":0},"i":{"x":0.58,"y":1},"s":[0],"t":24},{"s":[0],"t":30}]},"sa":{"a":0,"k":0},"o":{"a":1,"k":[{"o":{"x":0,"y":0},"i":{"x":0.58,"y":1},"s":[100],"t":0},{"o":{"x":0.65,"y":0},"i":{"x":0.35,"y":0},"s":[100],"t":18},{"o":{"x":0,"y":0},"i":{"x":0.58,"y":1},"s":[100],"t":24},{"s":[100],"t":30}]}},"shapes":[{"ty":"sh","bm":0,"hd":false,"nm":"","d":1,"ks":{"a":1,"k":[{"o":{"x":0,"y":0},"i":{"x":0.58,"y":1},"s":[{"c":true,"i":[[0,0],[0,0],[0,0],[0,0],[0,0]],"o":[[0,0],[0,0],[0,0],[0,0],[0,0]],"v":[[0,0],[515.25,0],[515.25,434.64],[0,434.64],[0,0]]}],"t":0},{"o":{"x":0.65,"y":0},"i":{"x":0.35,"y":0},"s":[{"c":true,"i":[[0,0],[0,0],[0,0],[0,0],[0,0]],"o":[[0,0],[0,0],[0,0],[0,0],[0,0]],"v":[[0,0],[553.56,0],[553.56,408.09],[0,408.09],[0,0]]}],"t":18},{"o":{"x":0,"y":0},"i":{"x":0.58,"y":1},"s":[{"c":true,"i":[[0,0],[0,0],[0,0],[0,0],[0,0]],"o":[[0,0],[0,0],[0,0],[0,0],[0,0]],"v":[[0,0],[478.46,0],[478.46,481.97],[0,481.97],[0,0]]}],"t":24},{"s":[{"c":true,"i":[[0,0],[0,0],[0,0],[0,0],[0,0]],"o":[[0,0],[0,0],[0,0],[0,0],[0,0]],"v":[[0,0],[515.25,0],[515.25,434.64],[0,434.64],[0,0]]}],"t":30}]}},{"ty":"fl","bm":0,"hd":false,"nm":"","c":{"a":1,"k":[{"o":{"x":0,"y":0},"i":{"x":0.58,"y":1},"s":[0.9844,0.9844,0.9844],"t":0},{"o":{"x":0.65,"y":0},"i":{"x":0.35,"y":0},"s":[0.9844,0.9844,0.9844],"t":18},{"o":{"x":0,"y":0},"i":{"x":0.58,"y":1},"s":[0.9844,0.9844,0.9844],"t":24},{"s":[0.9844,0.9844,0.9844],"t":30}]},"r":1,"o":{"a":1,"k":[{"o":{"x":0,"y":0},"i":{"x":0.58,"y":1},"s":[100],"t":0},{"o":{"x":0.65,"y":0},"i":{"x":0.35,"y":0},"s":[100],"t":18},{"o":{"x":0,"y":0},"i":{"x":0.58,"y":1},"s":[100],"t":24},{"s":[100],"t":30}]}}],"ind":34},{"ty":4,"nm":"2 / Group / Vector","sr":1,"st":0,"op":31,"ip":0,"hd":false,"ddd":0,"bm":0,"hasMask":false,"ao":0,"ks":{"a":{"a":1,"k":[{"o":{"x":0,"y":0},"i":{"x":0.58,"y":1},"s":[276.64,199.52],"t":0},{"o":{"x":0.65,"y":0},"i":{"x":0.35,"y":0},"s":[297.21,187.34],"t":18},{"o":{"x":0,"y":0},"i":{"x":0.58,"y":1},"s":[256.89,221.25],"t":24},{"s":[276.64,199.52],"t":30}]},"s":{"a":1,"k":[{"o":{"x":0,"y":0},"i":{"x":0.58,"y":1},"s":[100,100],"t":0},{"o":{"x":0.65,"y":0},"i":{"x":0.35,"y":0},"s":[100,100],"t":18},{"o":{"x":0,"y":0},"i":{"x":0.58,"y":1},"s":[100,100],"t":24},{"s":[100,100],"t":30}]},"sk":{"a":0,"k":0},"p":{"a":1,"k":[{"o":{"x":0,"y":0},"i":{"x":0.58,"y":1},"s":[557.34,572.96],"t":0},{"o":{"x":0.65,"y":0},"i":{"x":0.35,"y":0},"s":[557.45,614.48],"t":18},{"o":{"x":0,"y":0},"i":{"x":0.58,"y":1},"s":[557.24,498.97],"t":24},{"s":[557.34,572.96],"t":30}]},"r":{"a":1,"k":[{"o":{"x":0,"y":0},"i":{"x":0.58,"y":1},"s":[0],"t":0},{"o":{"x":0.65,"y":0},"i":{"x":0.35,"y":0},"s":[0],"t":18},{"o":{"x":0,"y":0},"i":{"x":0.58,"y":1},"s":[0],"t":24},{"s":[0],"t":30}]},"sa":{"a":0,"k":0},"o":{"a":1,"k":[{"o":{"x":0,"y":0},"i":{"x":0.58,"y":1},"s":[100],"t":0},{"o":{"x":0.65,"y":0},"i":{"x":0.35,"y":0},"s":[100],"t":18},{"o":{"x":0,"y":0},"i":{"x":0.58,"y":1},"s":[100],"t":24},{"s":[100],"t":30}]}},"shapes":[{"ty":"sh","bm":0,"hd":false,"nm":"","d":1,"ks":{"a":1,"k":[{"o":{"x":0,"y":0},"i":{"x":0.58,"y":1},"s":[{"c":true,"i":[[0,0],[0,0],[0,0],[0,0]],"o":[[0,0],[0,0],[0,0],[0,0]],"v":[[553.28,399.05],[0,399.05],[276.64,0],[553.28,399.05]]}],"t":0},{"o":{"x":0.65,"y":0},"i":{"x":0.35,"y":0},"s":[{"c":true,"i":[[0,0],[0,0],[0,0],[0,0]],"o":[[0,0],[0,0],[0,0],[0,0]],"v":[[594.42,374.67],[0,374.67],[297.21,0],[594.42,374.67]]}],"t":18},{"o":{"x":0,"y":0},"i":{"x":0.58,"y":1},"s":[{"c":true,"i":[[0,0],[0,0],[0,0],[0,0]],"o":[[0,0],[0,0],[0,0],[0,0]],"v":[[513.78,442.51],[0,442.51],[256.89,0],[513.78,442.51]]}],"t":24},{"s":[{"c":true,"i":[[0,0],[0,0],[0,0],[0,0]],"o":[[0,0],[0,0],[0,0],[0,0]],"v":[[553.28,399.05],[0,399.05],[276.64,0],[553.28,399.05]]}],"t":30}]}},{"ty":"fl","bm":0,"hd":false,"nm":"","c":{"a":1,"k":[{"o":{"x":0,"y":0},"i":{"x":0.58,"y":1},"s":[0.9844,0.9844,0.9844],"t":0},{"o":{"x":0.65,"y":0},"i":{"x":0.35,"y":0},"s":[0.9844,0.9844,0.9844],"t":18},{"o":{"x":0,"y":0},"i":{"x":0.58,"y":1},"s":[0.9844,0.9844,0.9844],"t":24},{"s":[0.9844,0.9844,0.9844],"t":30}]},"r":1,"o":{"a":1,"k":[{"o":{"x":0,"y":0},"i":{"x":0.58,"y":1},"s":[100],"t":0},{"o":{"x":0.65,"y":0},"i":{"x":0.35,"y":0},"s":[100],"t":18},{"o":{"x":0,"y":0},"i":{"x":0.58,"y":1},"s":[100],"t":24},{"s":[100],"t":30}]}}],"ind":35}],"v":"5.7.0","fr":30,"op":30.120000899769366,"ip":0,"assets":[]}